{
  "slug": "nogawa-park",
  "spot": {
    "slug": "nogawa-park",
    "name": "野川公園",
    "prefecture": "東京都",
    "city": "調布市",
    "access": "西武多摩川線 新小金井駅・多磨駅から徒歩15分。バス便もあり。",
    "course_type": "loop",
    "distance_m": 2655,
    "elevation_gain_m": 16,
    "hasGpx": true,
    "hasGuide": false,
    "pointCount": 774,
    "gpxDistanceM": 2655,
    "distanceDifferencePct": 0,
    "closureGapM": 30,
    "hasGpxElevation": true,
    "detectedCourseType": "loop",
    "issues": []
  },
  "collectedAt": "2026-07-13T09:18:03.793Z",
  "sources": {
    "stations": "https://express.heartrails.com/api.html",
    "photos": "https://commons.wikimedia.org/wiki/Commons:API/MediaWiki"
  },
  "samples": [
    {
      "fraction": 0,
      "point": {
        "lat": 35.680421,
        "lng": 139.523606,
        "ele": 49.8
      },
      "stations": [
        {
          "name": "多磨",
          "prefecture": "東京都",
          "line": "西武多摩川線",
          "x": 139.51713,
          "y": 35.676821,
          "postal": "1830004",
          "distance": "710m",
          "prev": "新小金井",
          "next": "白糸台"
        },
        {
          "name": "新小金井",
          "prefecture": "東京都",
          "line": "西武多摩川線",
          "x": 139.526603,
          "y": 35.695908,
          "postal": "1840011",
          "distance": "1750m",
          "prev": "武蔵境",
          "next": "多磨"
        },
        {
          "name": "白糸台",
          "prefecture": "東京都",
          "line": "西武多摩川線",
          "x": 139.509862,
          "y": 35.666517,
          "postal": "1830011",
          "distance": "1990m",
          "prev": "多磨",
          "next": "競艇場前"
        }
      ],
      "photos": [
        {
          "title": "1 Chome-3 Nomizu, Chōfu-shi, Tōkyō-to 182-0031, Japan - panoramio",
          "description": "1 Chome-3 Nomizu, Chōfu-shi, Tōkyō-to 182-0031, Japan",
          "url": "https://upload.wikimedia.org/wikipedia/commons/thumb/b/b0/1_Chome-3_Nomizu%2C_Ch%C5%8Dfu-shi%2C_T%C5%8Dky%C5%8D-to_182-0031%2C_Japan_-_panoramio.jpg/960px-1_Chome-3_Nomizu%2C_Ch%C5%8Dfu-shi%2C_T%C5%8Dky%C5%8D-to_182-0031%2C_Japan_-_panoramio.jpg",
          "sourceUrl": "https://commons.wikimedia.org/wiki/File:1_Chome-3_Nomizu,_Ch%C5%8Dfu-shi,_T%C5%8Dky%C5%8D-to_182-0031,_Japan_-_panoramio.jpg",
          "credit": "Hiroyuki Sato",
          "license": "CC BY-SA 3.0",
          "gps": {
            "lat": 35.681057,
            "lng": 139.525395
          }
        },
        {
          "title": "ASIJ Front Entrance",
          "description": "The American School in Japan (ASIJ)",
          "url": "https://upload.wikimedia.org/wikipedia/commons/thumb/f/fd/ASIJ_Front_Entrance.jpg/960px-ASIJ_Front_Entrance.jpg",
          "sourceUrl": "https://commons.wikimedia.org/wiki/File:ASIJ_Front_Entrance.jpg",
          "credit": "Calton",
          "license": "CC BY-SA 4.0",
          "gps": {
            "lat": 35.68019,
            "lng": 139.52168
          }
        },
        {
          "title": "ASIJ forecourt",
          "description": "Forecourt of the American School in Japan, in Tokyo",
          "url": "https://upload.wikimedia.org/wikipedia/commons/thumb/1/1e/ASIJ_forecourt.jpg/960px-ASIJ_forecourt.jpg",
          "sourceUrl": "https://commons.wikimedia.org/wiki/File:ASIJ_forecourt.jpg",
          "credit": "Calton",
          "license": "CC BY-SA 4.0",
          "gps": {
            "lat": 35.680675,
            "lng": 139.521592
          }
        },
        {
          "title": "1 Chome-3 Nomizu, Chōfu-shi, Tōkyō-to 182-0031, Japan - panoramio (2)",
          "description": "1 Chome-3 Nomizu, Chōfu-shi, Tōkyō-to 182-0031, Japan",
          "url": "https://upload.wikimedia.org/wikipedia/commons/thumb/9/92/1_Chome-3_Nomizu%2C_Ch%C5%8Dfu-shi%2C_T%C5%8Dky%C5%8D-to_182-0031%2C_Japan_-_panoramio_%282%29.jpg/960px-1_Chome-3_Nomizu%2C_Ch%C5%8Dfu-shi%2C_T%C5%8Dky%C5%8D-to_182-0031%2C_Japan_-_panoramio_%282%29.jpg",
          "sourceUrl": "https://commons.wikimedia.org/wiki/File:1_Chome-3_Nomizu,_Ch%C5%8Dfu-shi,_T%C5%8Dky%C5%8D-to_182-0031,_Japan_-_panoramio_(2).jpg",
          "credit": "Hiroyuki Sato",
          "license": "CC BY-SA 3.0",
          "gps": {
            "lat": 35.679667,
            "lng": 139.5245
          }
        },
        {
          "title": "都立野川公園・鯉のぼり 2012.04.29 12-24 - panoramio",
          "description": "都立野川公園・鯉のぼり 2012.04.29 12:24",
          "url": "https://upload.wikimedia.org/wikipedia/commons/thumb/f/f3/%E9%83%BD%E7%AB%8B%E9%87%8E%E5%B7%9D%E5%85%AC%E5%9C%92%E3%83%BB%E9%AF%89%E3%81%AE%E3%81%BC%E3%82%8A_2012.04.29_12-24_-_panoramio.jpg/960px-%E9%83%BD%E7%AB%8B%E9%87%8E%E5%B7%9D%E5%85%AC%E5%9C%92%E3%83%BB%E9%AF%89%E3%81%AE%E3%81%BC%E3%82%8A_2012.04.29_12-24_-_panoramio.jpg",
          "sourceUrl": "https://commons.wikimedia.org/wiki/File:%E9%83%BD%E7%AB%8B%E9%87%8E%E5%B7%9D%E5%85%AC%E5%9C%92%E3%83%BB%E9%AF%89%E3%81%AE%E3%81%BC%E3%82%8A_2012.04.29_12-24_-_panoramio.jpg",
          "credit": "Mitsuyoshi Kondo",
          "license": "CC BY 3.0",
          "gps": {
            "lat": 35.680925,
            "lng": 139.525463
          }
        },
        {
          "title": "1 Chome-3 Nomizu, Chōfu-shi, Tōkyō-to 182-0031, Japan - panoramio (4)",
          "description": "1 Chome-3 Nomizu, Chōfu-shi, Tōkyō-to 182-0031, Japan",
          "url": "https://upload.wikimedia.org/wikipedia/commons/thumb/c/c3/1_Chome-3_Nomizu%2C_Ch%C5%8Dfu-shi%2C_T%C5%8Dky%C5%8D-to_182-0031%2C_Japan_-_panoramio_%284%29.jpg/960px-1_Chome-3_Nomizu%2C_Ch%C5%8Dfu-shi%2C_T%C5%8Dky%C5%8D-to_182-0031%2C_Japan_-_panoramio_%284%29.jpg",
          "sourceUrl": "https://commons.wikimedia.org/wiki/File:1_Chome-3_Nomizu,_Ch%C5%8Dfu-shi,_T%C5%8Dky%C5%8D-to_182-0031,_Japan_-_panoramio_(4).jpg",
          "credit": "Hiroyuki Sato",
          "license": "CC BY-SA 3.0",
          "gps": {
            "lat": 35.680667,
            "lng": 139.524667
          }
        },
        {
          "title": "1 Chome-3 Nomizu, Chōfu-shi, Tōkyō-to 182-0031, Japan - panoramio (5)",
          "description": "1 Chome-3 Nomizu, Chōfu-shi, Tōkyō-to 182-0031, Japan",
          "url": "https://upload.wikimedia.org/wikipedia/commons/thumb/5/50/1_Chome-3_Nomizu%2C_Ch%C5%8Dfu-shi%2C_T%C5%8Dky%C5%8D-to_182-0031%2C_Japan_-_panoramio_%285%29.jpg/960px-1_Chome-3_Nomizu%2C_Ch%C5%8Dfu-shi%2C_T%C5%8Dky%C5%8D-to_182-0031%2C_Japan_-_panoramio_%285%29.jpg",
          "sourceUrl": "https://commons.wikimedia.org/wiki/File:1_Chome-3_Nomizu,_Ch%C5%8Dfu-shi,_T%C5%8Dky%C5%8D-to_182-0031,_Japan_-_panoramio_(5).jpg",
          "credit": "Hiroyuki Sato",
          "license": "CC BY-SA 3.0",
          "gps": {
            "lat": 35.679667,
            "lng": 139.524333
          }
        },
        {
          "title": "1 Chome-3 Nomizu, Chōfu-shi, Tōkyō-to 182-0031, Japan - panoramio (6)",
          "description": "1 Chome-3 Nomizu, Chōfu-shi, Tōkyō-to 182-0031, Japan",
          "url": "https://upload.wikimedia.org/wikipedia/commons/thumb/0/0b/1_Chome-3_Nomizu%2C_Ch%C5%8Dfu-shi%2C_T%C5%8Dky%C5%8D-to_182-0031%2C_Japan_-_panoramio_%286%29.jpg/960px-1_Chome-3_Nomizu%2C_Ch%C5%8Dfu-shi%2C_T%C5%8Dky%C5%8D-to_182-0031%2C_Japan_-_panoramio_%286%29.jpg",
          "sourceUrl": "https://commons.wikimedia.org/wiki/File:1_Chome-3_Nomizu,_Ch%C5%8Dfu-shi,_T%C5%8Dky%C5%8D-to_182-0031,_Japan_-_panoramio_(6).jpg",
          "credit": "Hiroyuki Sato",
          "license": "CC BY-SA 3.0",
          "gps": {
            "lat": 35.680333,
            "lng": 139.524667
          }
        }
      ]
    },
    {
      "fraction": 0.2,
      "point": {
        "lat": 35.68131159851981,
        "lng": 139.52900250299635,
        "ele": 49.2
      },
      "stations": [
        {
          "name": "多磨",
          "prefecture": "東京都",
          "line": "西武多摩川線",
          "x": 139.51713,
          "y": 35.676821,
          "postal": "1830004",
          "distance": "1180m",
          "prev": "新小金井",
          "next": "白糸台"
        },
        {
          "name": "新小金井",
          "prefecture": "東京都",
          "line": "西武多摩川線",
          "x": 139.526603,
          "y": 35.695908,
          "postal": "1840011",
          "distance": "1640m",
          "prev": "武蔵境",
          "next": "多磨"
        },
        {
          "name": "東小金井",
          "prefecture": "東京都",
          "line": "JR中央線",
          "x": 139.524837,
          "y": 35.701643,
          "postal": "1840002",
          "distance": "2290m",
          "prev": "武蔵境",
          "next": "武蔵小金井"
        }
      ],
      "photos": [
        {
          "title": "野川 - panoramio (18)",
          "description": "野川",
          "url": "https://upload.wikimedia.org/wikipedia/commons/thumb/3/3f/%E9%87%8E%E5%B7%9D_-_panoramio_%2818%29.jpg/960px-%E9%87%8E%E5%B7%9D_-_panoramio_%2818%29.jpg",
          "sourceUrl": "https://commons.wikimedia.org/wiki/File:%E9%87%8E%E5%B7%9D_-_panoramio_(18).jpg",
          "credit": "珈琲牛乳",
          "license": "CC BY 3.0",
          "gps": {
            "lat": 35.680589,
            "lng": 139.529824
          }
        },
        {
          "title": "野川 - panoramio (19)",
          "description": "野川",
          "url": "https://upload.wikimedia.org/wikipedia/commons/thumb/9/93/%E9%87%8E%E5%B7%9D_-_panoramio_%2819%29.jpg/960px-%E9%87%8E%E5%B7%9D_-_panoramio_%2819%29.jpg",
          "sourceUrl": "https://commons.wikimedia.org/wiki/File:%E9%87%8E%E5%B7%9D_-_panoramio_(19).jpg",
          "credit": "珈琲牛乳",
          "license": "CC BY 3.0",
          "gps": {
            "lat": 35.680616,
            "lng": 139.529947
          }
        },
        {
          "title": "Ford Thunderbird - panoramio",
          "description": "Ford Thunderbird",
          "url": "https://upload.wikimedia.org/wikipedia/commons/thumb/3/34/Ford_Thunderbird_-_panoramio.jpg/960px-Ford_Thunderbird_-_panoramio.jpg",
          "sourceUrl": "https://commons.wikimedia.org/wiki/File:Ford_Thunderbird_-_panoramio.jpg",
          "credit": "珈琲牛乳",
          "license": "CC BY 3.0",
          "gps": {
            "lat": 35.680387,
            "lng": 139.529761
          }
        },
        {
          "title": "野川 - panoramio (20)",
          "description": "​野川",
          "url": "https://upload.wikimedia.org/wikipedia/commons/thumb/e/e5/%E9%87%8E%E5%B7%9D_-_panoramio_%2820%29.jpg/960px-%E9%87%8E%E5%B7%9D_-_panoramio_%2820%29.jpg",
          "sourceUrl": "https://commons.wikimedia.org/wiki/File:%E9%87%8E%E5%B7%9D_-_panoramio_(20).jpg",
          "credit": "珈琲牛乳",
          "license": "CC BY 3.0",
          "gps": {
            "lat": 35.680589,
            "lng": 139.529824
          }
        },
        {
          "title": "Ford Thunderbird - panoramio (1)",
          "description": "Ford Thunderbird",
          "url": "https://upload.wikimedia.org/wikipedia/commons/thumb/d/d2/Ford_Thunderbird_-_panoramio_%281%29.jpg/960px-Ford_Thunderbird_-_panoramio_%281%29.jpg",
          "sourceUrl": "https://commons.wikimedia.org/wiki/File:Ford_Thunderbird_-_panoramio_(1).jpg",
          "credit": "珈琲牛乳",
          "license": "CC BY 3.0",
          "gps": {
            "lat": 35.68044,
            "lng": 139.529753
          }
        },
        {
          "title": "野川 - panoramio (21)",
          "description": "野川",
          "url": "https://upload.wikimedia.org/wikipedia/commons/thumb/4/45/%E9%87%8E%E5%B7%9D_-_panoramio_%2821%29.jpg/960px-%E9%87%8E%E5%B7%9D_-_panoramio_%2821%29.jpg",
          "sourceUrl": "https://commons.wikimedia.org/wiki/File:%E9%87%8E%E5%B7%9D_-_panoramio_(21).jpg",
          "credit": "珈琲牛乳",
          "license": "CC BY 3.0",
          "gps": {
            "lat": 35.681289,
            "lng": 139.529495
          }
        },
        {
          "title": "野川 - panoramio (23)",
          "description": "野川",
          "url": "https://upload.wikimedia.org/wikipedia/commons/thumb/4/4f/%E9%87%8E%E5%B7%9D_-_panoramio_%2823%29.jpg/960px-%E9%87%8E%E5%B7%9D_-_panoramio_%2823%29.jpg",
          "sourceUrl": "https://commons.wikimedia.org/wiki/File:%E9%87%8E%E5%B7%9D_-_panoramio_(23).jpg",
          "credit": "珈琲牛乳",
          "license": "CC BY 3.0",
          "gps": {
            "lat": 35.681806,
            "lng": 139.529401
          }
        },
        {
          "title": "野川 - panoramio (24)",
          "description": "野川",
          "url": "https://upload.wikimedia.org/wikipedia/commons/thumb/5/54/%E9%87%8E%E5%B7%9D_-_panoramio_%2824%29.jpg/960px-%E9%87%8E%E5%B7%9D_-_panoramio_%2824%29.jpg",
          "sourceUrl": "https://commons.wikimedia.org/wiki/File:%E9%87%8E%E5%B7%9D_-_panoramio_(24).jpg",
          "credit": "珈琲牛乳",
          "license": "CC BY 3.0",
          "gps": {
            "lat": 35.682086,
            "lng": 139.529207
          }
        }
      ]
    },
    {
      "fraction": 0.4,
      "point": {
        "lat": 35.68428821311703,
        "lng": 139.52626367063735,
        "ele": 47
      },
      "stations": [
        {
          "name": "多磨",
          "prefecture": "東京都",
          "line": "西武多摩川線",
          "x": 139.51713,
          "y": 35.676821,
          "postal": "1830004",
          "distance": "1170m",
          "prev": "新小金井",
          "next": "白糸台"
        },
        {
          "name": "新小金井",
          "prefecture": "東京都",
          "line": "西武多摩川線",
          "x": 139.526603,
          "y": 35.695908,
          "postal": "1840011",
          "distance": "1290m",
          "prev": "武蔵境",
          "next": "多磨"
        },
        {
          "name": "東小金井",
          "prefecture": "東京都",
          "line": "JR中央線",
          "x": 139.524837,
          "y": 35.701643,
          "postal": "1840002",
          "distance": "1940m",
          "prev": "武蔵境",
          "next": "武蔵小金井"
        }
      ],
      "photos": [
        {
          "title": "Vehicle (6340191320)",
          "description": "vehicle",
          "url": "https://upload.wikimedia.org/wikipedia/commons/thumb/f/fd/Vehicle_%286340191320%29.jpg/960px-Vehicle_%286340191320%29.jpg",
          "sourceUrl": "https://commons.wikimedia.org/wiki/File:Vehicle_(6340191320).jpg",
          "credit": "Mr. Brian",
          "license": "CC BY 2.0",
          "gps": {
            "lat": 35.684167,
            "lng": 139.524333
          }
        },
        {
          "title": "野川公園 - panoramio",
          "description": "野川公園",
          "url": "https://upload.wikimedia.org/wikipedia/commons/thumb/9/9b/%E9%87%8E%E5%B7%9D%E5%85%AC%E5%9C%92_-_panoramio.jpg/960px-%E9%87%8E%E5%B7%9D%E5%85%AC%E5%9C%92_-_panoramio.jpg",
          "sourceUrl": "https://commons.wikimedia.org/wiki/File:%E9%87%8E%E5%B7%9D%E5%85%AC%E5%9C%92_-_panoramio.jpg",
          "credit": "Hiroyuki Sato",
          "license": "CC BY-SA 3.0",
          "gps": {
            "lat": 35.685868,
            "lng": 139.525343
          }
        },
        {
          "title": "1 Chome-3 Nomizu, Chōfu-shi, Tōkyō-to 182-0031, Japan - panoramio (3)",
          "description": "1 Chome-3 Nomizu, Chōfu-shi, Tōkyō-to 182-0031, Japan",
          "url": "https://upload.wikimedia.org/wikipedia/commons/thumb/2/27/1_Chome-3_Nomizu%2C_Ch%C5%8Dfu-shi%2C_T%C5%8Dky%C5%8D-to_182-0031%2C_Japan_-_panoramio_%283%29.jpg/960px-1_Chome-3_Nomizu%2C_Ch%C5%8Dfu-shi%2C_T%C5%8Dky%C5%8D-to_182-0031%2C_Japan_-_panoramio_%283%29.jpg",
          "sourceUrl": "https://commons.wikimedia.org/wiki/File:1_Chome-3_Nomizu,_Ch%C5%8Dfu-shi,_T%C5%8Dky%C5%8D-to_182-0031,_Japan_-_panoramio_(3).jpg",
          "credit": "Hiroyuki Sato",
          "license": "CC BY-SA 3.0",
          "gps": {
            "lat": 35.681667,
            "lng": 139.527
          }
        },
        {
          "title": "都立野川公園・鯉のぼり 2012.04.29 12-16 - panoramio",
          "description": "都立野川公園・鯉のぼり 2012.04.29 12:16",
          "url": "https://upload.wikimedia.org/wikipedia/commons/thumb/1/1b/%E9%83%BD%E7%AB%8B%E9%87%8E%E5%B7%9D%E5%85%AC%E5%9C%92%E3%83%BB%E9%AF%89%E3%81%AE%E3%81%BC%E3%82%8A_2012.04.29_12-16_-_panoramio.jpg/960px-%E9%83%BD%E7%AB%8B%E9%87%8E%E5%B7%9D%E5%85%AC%E5%9C%92%E3%83%BB%E9%AF%89%E3%81%AE%E3%81%BC%E3%82%8A_2012.04.29_12-16_-_panoramio.jpg",
          "sourceUrl": "https://commons.wikimedia.org/wiki/File:%E9%83%BD%E7%AB%8B%E9%87%8E%E5%B7%9D%E5%85%AC%E5%9C%92%E3%83%BB%E9%AF%89%E3%81%AE%E3%81%BC%E3%82%8A_2012.04.29_12-16_-_panoramio.jpg",
          "credit": "Mitsuyoshi Kondo",
          "license": "CC BY 3.0",
          "gps": {
            "lat": 35.681644,
            "lng": 139.525582
          }
        },
        {
          "title": "野川 - panoramio (34)",
          "description": "野川",
          "url": "https://upload.wikimedia.org/wikipedia/commons/thumb/f/f5/%E9%87%8E%E5%B7%9D_-_panoramio_%2834%29.jpg/960px-%E9%87%8E%E5%B7%9D_-_panoramio_%2834%29.jpg",
          "sourceUrl": "https://commons.wikimedia.org/wiki/File:%E9%87%8E%E5%B7%9D_-_panoramio_(34).jpg",
          "credit": "珈琲牛乳",
          "license": "CC BY 3.0",
          "gps": {
            "lat": 35.683554,
            "lng": 139.529415
          }
        },
        {
          "title": "野川 - panoramio (35)",
          "description": "野川",
          "url": "https://upload.wikimedia.org/wikipedia/commons/thumb/9/90/%E9%87%8E%E5%B7%9D_-_panoramio_%2835%29.jpg/960px-%E9%87%8E%E5%B7%9D_-_panoramio_%2835%29.jpg",
          "sourceUrl": "https://commons.wikimedia.org/wiki/File:%E9%87%8E%E5%B7%9D_-_panoramio_(35).jpg",
          "credit": "珈琲牛乳",
          "license": "CC BY 3.0",
          "gps": {
            "lat": 35.683514,
            "lng": 139.529472
          }
        },
        {
          "title": "野川 - panoramio (36)",
          "description": "野川",
          "url": "https://upload.wikimedia.org/wikipedia/commons/thumb/d/d0/%E9%87%8E%E5%B7%9D_-_panoramio_%2836%29.jpg/960px-%E9%87%8E%E5%B7%9D_-_panoramio_%2836%29.jpg",
          "sourceUrl": "https://commons.wikimedia.org/wiki/File:%E9%87%8E%E5%B7%9D_-_panoramio_(36).jpg",
          "credit": "珈琲牛乳",
          "license": "CC BY 3.0",
          "gps": {
            "lat": 35.683656,
            "lng": 139.528244
          }
        },
        {
          "title": "野川 - panoramio (38)",
          "description": "野川",
          "url": "https://upload.wikimedia.org/wikipedia/commons/thumb/7/72/%E9%87%8E%E5%B7%9D_-_panoramio_%2838%29.jpg/960px-%E9%87%8E%E5%B7%9D_-_panoramio_%2838%29.jpg",
          "sourceUrl": "https://commons.wikimedia.org/wiki/File:%E9%87%8E%E5%B7%9D_-_panoramio_(38).jpg",
          "credit": "珈琲牛乳",
          "license": "CC BY 3.0",
          "gps": {
            "lat": 35.683657,
            "lng": 139.528221
          }
        }
      ]
    },
    {
      "fraction": 0.6,
      "point": {
        "lat": 35.68818420071522,
        "lng": 139.52355544116006,
        "ele": 48.7
      },
      "stations": [
        {
          "name": "新小金井",
          "prefecture": "東京都",
          "line": "西武多摩川線",
          "x": 139.526603,
          "y": 35.695908,
          "postal": "1840011",
          "distance": "900m",
          "prev": "武蔵境",
          "next": "多磨"
        },
        {
          "name": "多磨",
          "prefecture": "東京都",
          "line": "西武多摩川線",
          "x": 139.51713,
          "y": 35.676821,
          "postal": "1830004",
          "distance": "1390m",
          "prev": "新小金井",
          "next": "白糸台"
        },
        {
          "name": "東小金井",
          "prefecture": "東京都",
          "line": "JR中央線",
          "x": 139.524837,
          "y": 35.701643,
          "postal": "1840002",
          "distance": "1500m",
          "prev": "武蔵境",
          "next": "武蔵小金井"
        }
      ],
      "photos": [
        {
          "title": "府中運転免許試験所となりの公園 - panoramio",
          "description": "府中運転免許試験所となりの公園",
          "url": "https://upload.wikimedia.org/wikipedia/commons/thumb/0/03/%E5%BA%9C%E4%B8%AD%E9%81%8B%E8%BB%A2%E5%85%8D%E8%A8%B1%E8%A9%A6%E9%A8%93%E6%89%80%E3%81%A8%E3%81%AA%E3%82%8A%E3%81%AE%E5%85%AC%E5%9C%92_-_panoramio.jpg/960px-%E5%BA%9C%E4%B8%AD%E9%81%8B%E8%BB%A2%E5%85%8D%E8%A8%B1%E8%A9%A6%E9%A8%93%E6%89%80%E3%81%A8%E3%81%AA%E3%82%8A%E3%81%AE%E5%85%AC%E5%9C%92_-_panoramio.jpg",
          "sourceUrl": "https://commons.wikimedia.org/wiki/File:%E5%BA%9C%E4%B8%AD%E9%81%8B%E8%BB%A2%E5%85%8D%E8%A8%B1%E8%A9%A6%E9%A8%93%E6%89%80%E3%81%A8%E3%81%AA%E3%82%8A%E3%81%AE%E5%85%AC%E5%9C%92_-_panoramio.jpg",
          "credit": "tinbotu",
          "license": "CC BY-SA 3.0",
          "gps": {
            "lat": 35.689639,
            "lng": 139.520667
          }
        },
        {
          "title": "野川公園 - panoramio",
          "description": "野川公園",
          "url": "https://upload.wikimedia.org/wikipedia/commons/thumb/9/9b/%E9%87%8E%E5%B7%9D%E5%85%AC%E5%9C%92_-_panoramio.jpg/960px-%E9%87%8E%E5%B7%9D%E5%85%AC%E5%9C%92_-_panoramio.jpg",
          "sourceUrl": "https://commons.wikimedia.org/wiki/File:%E9%87%8E%E5%B7%9D%E5%85%AC%E5%9C%92_-_panoramio.jpg",
          "credit": "Hiroyuki Sato",
          "license": "CC BY-SA 3.0",
          "gps": {
            "lat": 35.685868,
            "lng": 139.525343
          }
        },
        {
          "title": "東八道路と野川公園の桜 - panoramio",
          "description": "東八道路と野川公園の桜",
          "url": "https://upload.wikimedia.org/wikipedia/commons/thumb/4/4e/%E6%9D%B1%E5%85%AB%E9%81%93%E8%B7%AF%E3%81%A8%E9%87%8E%E5%B7%9D%E5%85%AC%E5%9C%92%E3%81%AE%E6%A1%9C_-_panoramio.jpg/960px-%E6%9D%B1%E5%85%AB%E9%81%93%E8%B7%AF%E3%81%A8%E9%87%8E%E5%B7%9D%E5%85%AC%E5%9C%92%E3%81%AE%E6%A1%9C_-_panoramio.jpg",
          "sourceUrl": "https://commons.wikimedia.org/wiki/File:%E6%9D%B1%E5%85%AB%E9%81%93%E8%B7%AF%E3%81%A8%E9%87%8E%E5%B7%9D%E5%85%AC%E5%9C%92%E3%81%AE%E6%A1%9C_-_panoramio.jpg",
          "credit": "Kiyo",
          "license": "CC BY-SA 3.0",
          "gps": {
            "lat": 35.68572,
            "lng": 139.522443
          }
        },
        {
          "title": "野川公園 - panoramio (1)",
          "description": "野川公園",
          "url": "https://upload.wikimedia.org/wikipedia/commons/thumb/7/7d/%E9%87%8E%E5%B7%9D%E5%85%AC%E5%9C%92_-_panoramio_%281%29.jpg/960px-%E9%87%8E%E5%B7%9D%E5%85%AC%E5%9C%92_-_panoramio_%281%29.jpg",
          "sourceUrl": "https://commons.wikimedia.org/wiki/File:%E9%87%8E%E5%B7%9D%E5%85%AC%E5%9C%92_-_panoramio_(1).jpg",
          "credit": "Hiroyuki Sato",
          "license": "CC BY-SA 3.0",
          "gps": {
            "lat": 35.686029,
            "lng": 139.522684
          }
        },
        {
          "title": "1 Chome Nomizu, Chōfu-shi, Tōkyō-to 182-0031, Japan - panoramio",
          "description": "1 Chome Nomizu, Chōfu-shi, Tōkyō-to 182-0031, Japan",
          "url": "https://upload.wikimedia.org/wikipedia/commons/thumb/c/c3/1_Chome_Nomizu%2C_Ch%C5%8Dfu-shi%2C_T%C5%8Dky%C5%8D-to_182-0031%2C_Japan_-_panoramio.jpg/960px-1_Chome_Nomizu%2C_Ch%C5%8Dfu-shi%2C_T%C5%8Dky%C5%8D-to_182-0031%2C_Japan_-_panoramio.jpg",
          "sourceUrl": "https://commons.wikimedia.org/wiki/File:1_Chome_Nomizu,_Ch%C5%8Dfu-shi,_T%C5%8Dky%C5%8D-to_182-0031,_Japan_-_panoramio.jpg",
          "credit": "Hiroyuki Sato",
          "license": "CC BY-SA 3.0",
          "gps": {
            "lat": 35.685833,
            "lng": 139.5225
          }
        },
        {
          "title": "2 Chome Nomizu, Chōfu-shi, Tōkyō-to 182-0031, Japan - panoramio",
          "description": "2 Chome Nomizu, Chōfu-shi, Tōkyō-to 182-0031, Japan",
          "url": "https://upload.wikimedia.org/wikipedia/commons/thumb/6/69/2_Chome_Nomizu%2C_Ch%C5%8Dfu-shi%2C_T%C5%8Dky%C5%8D-to_182-0031%2C_Japan_-_panoramio.jpg/960px-2_Chome_Nomizu%2C_Ch%C5%8Dfu-shi%2C_T%C5%8Dky%C5%8D-to_182-0031%2C_Japan_-_panoramio.jpg",
          "sourceUrl": "https://commons.wikimedia.org/wiki/File:2_Chome_Nomizu,_Ch%C5%8Dfu-shi,_T%C5%8Dky%C5%8D-to_182-0031,_Japan_-_panoramio.jpg",
          "credit": "Hiroyuki Sato",
          "license": "CC BY-SA 3.0",
          "gps": {
            "lat": 35.686333,
            "lng": 139.522333
          }
        },
        {
          "title": "野川 - panoramio (50)",
          "description": "野川",
          "url": "https://upload.wikimedia.org/wikipedia/commons/thumb/c/c5/%E9%87%8E%E5%B7%9D_-_panoramio_%2850%29.jpg/960px-%E9%87%8E%E5%B7%9D_-_panoramio_%2850%29.jpg",
          "sourceUrl": "https://commons.wikimedia.org/wiki/File:%E9%87%8E%E5%B7%9D_-_panoramio_(50).jpg",
          "credit": "珈琲牛乳",
          "license": "CC BY 3.0",
          "gps": {
            "lat": 35.687023,
            "lng": 139.525869
          }
        },
        {
          "title": "野川 - panoramio (51)",
          "description": "野川",
          "url": "https://upload.wikimedia.org/wikipedia/commons/thumb/f/fc/%E9%87%8E%E5%B7%9D_-_panoramio_%2851%29.jpg/960px-%E9%87%8E%E5%B7%9D_-_panoramio_%2851%29.jpg",
          "sourceUrl": "https://commons.wikimedia.org/wiki/File:%E9%87%8E%E5%B7%9D_-_panoramio_(51).jpg",
          "credit": "珈琲牛乳",
          "license": "CC BY 3.0",
          "gps": {
            "lat": 35.688259,
            "lng": 139.523276
          }
        }
      ]
    },
    {
      "fraction": 0.8,
      "point": {
        "lat": 35.68426867380463,
        "lng": 139.52209568683082,
        "ele": 50.5
      },
      "stations": [
        {
          "name": "多磨",
          "prefecture": "東京都",
          "line": "西武多摩川線",
          "x": 139.51713,
          "y": 35.676821,
          "postal": "1830004",
          "distance": "940m",
          "prev": "新小金井",
          "next": "白糸台"
        },
        {
          "name": "新小金井",
          "prefecture": "東京都",
          "line": "西武多摩川線",
          "x": 139.526603,
          "y": 35.695908,
          "postal": "1840011",
          "distance": "1360m",
          "prev": "武蔵境",
          "next": "多磨"
        },
        {
          "name": "東小金井",
          "prefecture": "東京都",
          "line": "JR中央線",
          "x": 139.524837,
          "y": 35.701643,
          "postal": "1840002",
          "distance": "1950m",
          "prev": "武蔵境",
          "next": "武蔵小金井"
        }
      ],
      "photos": [
        {
          "title": "Vehicle (6340191320)",
          "description": "vehicle",
          "url": "https://upload.wikimedia.org/wikipedia/commons/thumb/f/fd/Vehicle_%286340191320%29.jpg/960px-Vehicle_%286340191320%29.jpg",
          "sourceUrl": "https://commons.wikimedia.org/wiki/File:Vehicle_(6340191320).jpg",
          "credit": "Mr. Brian",
          "license": "CC BY 2.0",
          "gps": {
            "lat": 35.684167,
            "lng": 139.524333
          }
        },
        {
          "title": "野川公園 - panoramio",
          "description": "野川公園",
          "url": "https://upload.wikimedia.org/wikipedia/commons/thumb/9/9b/%E9%87%8E%E5%B7%9D%E5%85%AC%E5%9C%92_-_panoramio.jpg/960px-%E9%87%8E%E5%B7%9D%E5%85%AC%E5%9C%92_-_panoramio.jpg",
          "sourceUrl": "https://commons.wikimedia.org/wiki/File:%E9%87%8E%E5%B7%9D%E5%85%AC%E5%9C%92_-_panoramio.jpg",
          "credit": "Hiroyuki Sato",
          "license": "CC BY-SA 3.0",
          "gps": {
            "lat": 35.685868,
            "lng": 139.525343
          }
        },
        {
          "title": "東八道路と野川公園の桜 - panoramio",
          "description": "東八道路と野川公園の桜",
          "url": "https://upload.wikimedia.org/wikipedia/commons/thumb/4/4e/%E6%9D%B1%E5%85%AB%E9%81%93%E8%B7%AF%E3%81%A8%E9%87%8E%E5%B7%9D%E5%85%AC%E5%9C%92%E3%81%AE%E6%A1%9C_-_panoramio.jpg/960px-%E6%9D%B1%E5%85%AB%E9%81%93%E8%B7%AF%E3%81%A8%E9%87%8E%E5%B7%9D%E5%85%AC%E5%9C%92%E3%81%AE%E6%A1%9C_-_panoramio.jpg",
          "sourceUrl": "https://commons.wikimedia.org/wiki/File:%E6%9D%B1%E5%85%AB%E9%81%93%E8%B7%AF%E3%81%A8%E9%87%8E%E5%B7%9D%E5%85%AC%E5%9C%92%E3%81%AE%E6%A1%9C_-_panoramio.jpg",
          "credit": "Kiyo",
          "license": "CC BY-SA 3.0",
          "gps": {
            "lat": 35.68572,
            "lng": 139.522443
          }
        },
        {
          "title": "野川公園 - panoramio (1)",
          "description": "野川公園",
          "url": "https://upload.wikimedia.org/wikipedia/commons/thumb/7/7d/%E9%87%8E%E5%B7%9D%E5%85%AC%E5%9C%92_-_panoramio_%281%29.jpg/960px-%E9%87%8E%E5%B7%9D%E5%85%AC%E5%9C%92_-_panoramio_%281%29.jpg",
          "sourceUrl": "https://commons.wikimedia.org/wiki/File:%E9%87%8E%E5%B7%9D%E5%85%AC%E5%9C%92_-_panoramio_(1).jpg",
          "credit": "Hiroyuki Sato",
          "license": "CC BY-SA 3.0",
          "gps": {
            "lat": 35.686029,
            "lng": 139.522684
          }
        },
        {
          "title": "ASIJ Front Entrance",
          "description": "The American School in Japan (ASIJ)",
          "url": "https://upload.wikimedia.org/wikipedia/commons/thumb/f/fd/ASIJ_Front_Entrance.jpg/960px-ASIJ_Front_Entrance.jpg",
          "sourceUrl": "https://commons.wikimedia.org/wiki/File:ASIJ_Front_Entrance.jpg",
          "credit": "Calton",
          "license": "CC BY-SA 4.0",
          "gps": {
            "lat": 35.68019,
            "lng": 139.52168
          }
        },
        {
          "title": "ASIJ forecourt",
          "description": "Forecourt of the American School in Japan, in Tokyo",
          "url": "https://upload.wikimedia.org/wikipedia/commons/thumb/1/1e/ASIJ_forecourt.jpg/960px-ASIJ_forecourt.jpg",
          "sourceUrl": "https://commons.wikimedia.org/wiki/File:ASIJ_forecourt.jpg",
          "credit": "Calton",
          "license": "CC BY-SA 4.0",
          "gps": {
            "lat": 35.680675,
            "lng": 139.521592
          }
        },
        {
          "title": "1 Chome Nomizu, Chōfu-shi, Tōkyō-to 182-0031, Japan - panoramio",
          "description": "1 Chome Nomizu, Chōfu-shi, Tōkyō-to 182-0031, Japan",
          "url": "https://upload.wikimedia.org/wikipedia/commons/thumb/c/c3/1_Chome_Nomizu%2C_Ch%C5%8Dfu-shi%2C_T%C5%8Dky%C5%8D-to_182-0031%2C_Japan_-_panoramio.jpg/960px-1_Chome_Nomizu%2C_Ch%C5%8Dfu-shi%2C_T%C5%8Dky%C5%8D-to_182-0031%2C_Japan_-_panoramio.jpg",
          "sourceUrl": "https://commons.wikimedia.org/wiki/File:1_Chome_Nomizu,_Ch%C5%8Dfu-shi,_T%C5%8Dky%C5%8D-to_182-0031,_Japan_-_panoramio.jpg",
          "credit": "Hiroyuki Sato",
          "license": "CC BY-SA 3.0",
          "gps": {
            "lat": 35.685833,
            "lng": 139.5225
          }
        },
        {
          "title": "都立野川公園・鯉のぼり 2012.04.29 12-16 - panoramio",
          "description": "都立野川公園・鯉のぼり 2012.04.29 12:16",
          "url": "https://upload.wikimedia.org/wikipedia/commons/thumb/1/1b/%E9%83%BD%E7%AB%8B%E9%87%8E%E5%B7%9D%E5%85%AC%E5%9C%92%E3%83%BB%E9%AF%89%E3%81%AE%E3%81%BC%E3%82%8A_2012.04.29_12-16_-_panoramio.jpg/960px-%E9%83%BD%E7%AB%8B%E9%87%8E%E5%B7%9D%E5%85%AC%E5%9C%92%E3%83%BB%E9%AF%89%E3%81%AE%E3%81%BC%E3%82%8A_2012.04.29_12-16_-_panoramio.jpg",
          "sourceUrl": "https://commons.wikimedia.org/wiki/File:%E9%83%BD%E7%AB%8B%E9%87%8E%E5%B7%9D%E5%85%AC%E5%9C%92%E3%83%BB%E9%AF%89%E3%81%AE%E3%81%BC%E3%82%8A_2012.04.29_12-16_-_panoramio.jpg",
          "credit": "Mitsuyoshi Kondo",
          "license": "CC BY 3.0",
          "gps": {
            "lat": 35.681644,
            "lng": 139.525582
          }
        }
      ]
    }
  ],
  "reviewStatus": "needs_review"
}
