{
  "slug": "oohori",
  "spot": {
    "slug": "oohori",
    "name": "大濠公園",
    "prefecture": "福岡県",
    "city": "福岡市中央区",
    "access": "福岡市地下鉄 大濠公園駅から徒歩約3分。",
    "course_type": "loop",
    "distance_m": 1968,
    "elevation_gain_m": 30,
    "hasGpx": true,
    "hasGuide": false,
    "pointCount": 429,
    "gpxDistanceM": 1968,
    "distanceDifferencePct": 0,
    "closureGapM": 4,
    "hasGpxElevation": true,
    "detectedCourseType": "loop",
    "issues": []
  },
  "collectedAt": "2026-07-13T09:18:52.483Z",
  "sources": {
    "stations": "https://express.heartrails.com/api.html",
    "photos": "https://commons.wikimedia.org/wiki/Commons:API/MediaWiki"
  },
  "samples": [
    {
      "fraction": 0,
      "point": {
        "lat": 33.585527,
        "lng": 130.378878,
        "ele": 3.2
      },
      "stations": [
        {
          "name": "大濠公園",
          "prefecture": "福岡県",
          "line": "福岡市空港線",
          "x": 130.378784,
          "y": 33.589957,
          "postal": "8100074",
          "distance": "490m",
          "prev": "唐人町",
          "next": "赤坂"
        },
        {
          "name": "六本松",
          "prefecture": "福岡県",
          "line": "福岡市七隈線",
          "x": 130.377287,
          "y": 33.577678,
          "postal": "8100044",
          "distance": "890m",
          "prev": "別府",
          "next": "桜坂"
        },
        {
          "name": "唐人町",
          "prefecture": "福岡県",
          "line": "福岡市空港線",
          "x": 130.370451,
          "y": 33.590235,
          "postal": "8100063",
          "distance": "940m",
          "prev": "西新",
          "next": "大濠公園"
        }
      ],
      "photos": [
        {
          "title": "Ohori Park before firework display 20150801-3",
          "description": "花火大会前の大濠公園",
          "url": "https://upload.wikimedia.org/wikipedia/commons/thumb/5/53/Ohori_Park_before_firework_display_20150801-3.JPG/960px-Ohori_Park_before_firework_display_20150801-3.JPG",
          "sourceUrl": "https://commons.wikimedia.org/wiki/File:Ohori_Park_before_firework_display_20150801-3.JPG",
          "credit": "そらみみ (Soramimi)",
          "license": "CC BY-SA 4.0",
          "gps": {
            "lat": 33.584914,
            "lng": 130.378753
          }
        },
        {
          "title": "Ohori Park at dusk 20170930-8",
          "description": "大濠公園の景色",
          "url": "https://upload.wikimedia.org/wikipedia/commons/thumb/7/76/Ohori_Park_at_dusk_20170930-8.jpg/960px-Ohori_Park_at_dusk_20170930-8.jpg",
          "sourceUrl": "https://commons.wikimedia.org/wiki/File:Ohori_Park_at_dusk_20170930-8.jpg",
          "credit": "そらみみ",
          "license": "CC BY-SA 4.0",
          "gps": {
            "lat": 33.585725,
            "lng": 130.378311
          }
        },
        {
          "title": "Ōhori Park The smoking area Ōhorikōen Chūō-ku Fukuoka 20260113 150049",
          "description": "Ōhori Park: The smoking area (Address: Ōhorikōen, Chūō-ku, Fukuoka-shi 8100051, Japan)",
          "url": "https://upload.wikimedia.org/wikipedia/commons/thumb/d/d7/%C5%8Chori_Park_The_smoking_area_%C5%8Chorik%C5%8Den_Ch%C5%AB%C5%8D-ku_Fukuoka_20260113_150049.jpg/960px-%C5%8Chori_Park_The_smoking_area_%C5%8Chorik%C5%8Den_Ch%C5%AB%C5%8D-ku_Fukuoka_20260113_150049.jpg",
          "sourceUrl": "https://commons.wikimedia.org/wiki/File:%C5%8Chori_Park_The_smoking_area_%C5%8Chorik%C5%8Den_Ch%C5%AB%C5%8D-ku_Fukuoka_20260113_150049.jpg",
          "credit": "Hirho",
          "license": "CC BY 4.0",
          "gps": {
            "lat": 33.58493,
            "lng": 130.37882
          }
        },
        {
          "title": "Ōhori Park The fitness trail Ōhorikōen Chūō-ku Fukuoka 20260427 171719",
          "description": "Ōhori Park: The fitness trail (Address: Ōhorikōen, Chūō-ku, Fukuoka-shi 8100051, Japan)",
          "url": "https://upload.wikimedia.org/wikipedia/commons/thumb/8/8e/%C5%8Chori_Park_The_fitness_trail_%C5%8Chorik%C5%8Den_Ch%C5%AB%C5%8D-ku_Fukuoka_20260427_171719.jpg/960px-%C5%8Chori_Park_The_fitness_trail_%C5%8Chorik%C5%8Den_Ch%C5%AB%C5%8D-ku_Fukuoka_20260427_171719.jpg",
          "sourceUrl": "https://commons.wikimedia.org/wiki/File:%C5%8Chori_Park_The_fitness_trail_%C5%8Chorik%C5%8Den_Ch%C5%AB%C5%8D-ku_Fukuoka_20260427_171719.jpg",
          "credit": "Hirho",
          "license": "CC BY 4.0",
          "gps": {
            "lat": 33.5855,
            "lng": 130.37882
          }
        },
        {
          "title": "Ōhori Park The bug zapper Ōhorikōen Chūō-ku Fukuoka 20260427 171344",
          "description": "Ōhori Park: The bug zapper (Address: Ōhorikōen, Chūō-ku, Fukuoka-shi 8100051, Japan)",
          "url": "https://upload.wikimedia.org/wikipedia/commons/thumb/b/bf/%C5%8Chori_Park_The_bug_zapper_%C5%8Chorik%C5%8Den_Ch%C5%AB%C5%8D-ku_Fukuoka_20260427_171344.jpg/960px-%C5%8Chori_Park_The_bug_zapper_%C5%8Chorik%C5%8Den_Ch%C5%AB%C5%8D-ku_Fukuoka_20260427_171344.jpg",
          "sourceUrl": "https://commons.wikimedia.org/wiki/File:%C5%8Chori_Park_The_bug_zapper_%C5%8Chorik%C5%8Den_Ch%C5%AB%C5%8D-ku_Fukuoka_20260427_171344.jpg",
          "credit": "Hirho",
          "license": "CC BY 4.0",
          "gps": {
            "lat": 33.58496,
            "lng": 130.3789
          }
        },
        {
          "title": "Ōhori Park The pine forest Ōhorikōen Chūō-ku Fukuoka 20260427 172244",
          "description": "Ōhori Park: The pine forest (Address: Ōhorikōen, Chūō-ku, Fukuoka-shi 8100051, Japan)",
          "url": "https://upload.wikimedia.org/wikipedia/commons/thumb/7/78/%C5%8Chori_Park_The_pine_forest_%C5%8Chorik%C5%8Den_Ch%C5%AB%C5%8D-ku_Fukuoka_20260427_172244.jpg/960px-%C5%8Chori_Park_The_pine_forest_%C5%8Chorik%C5%8Den_Ch%C5%AB%C5%8D-ku_Fukuoka_20260427_172244.jpg",
          "sourceUrl": "https://commons.wikimedia.org/wiki/File:%C5%8Chori_Park_The_pine_forest_%C5%8Chorik%C5%8Den_Ch%C5%AB%C5%8D-ku_Fukuoka_20260427_172244.jpg",
          "credit": "Hirho",
          "license": "CC BY 4.0",
          "gps": {
            "lat": 33.58549,
            "lng": 130.3785
          }
        },
        {
          "title": "Ōhori Park The pine forest Ōhorikōen Chūō-ku Fukuoka 20260427 172621",
          "description": "Ōhori Park: The pine forest (Address: Ōhorikōen, Chūō-ku, Fukuoka-shi 8100051, Japan)",
          "url": "https://upload.wikimedia.org/wikipedia/commons/thumb/e/e2/%C5%8Chori_Park_The_pine_forest_%C5%8Chorik%C5%8Den_Ch%C5%AB%C5%8D-ku_Fukuoka_20260427_172621.jpg/960px-%C5%8Chori_Park_The_pine_forest_%C5%8Chorik%C5%8Den_Ch%C5%AB%C5%8D-ku_Fukuoka_20260427_172621.jpg",
          "sourceUrl": "https://commons.wikimedia.org/wiki/File:%C5%8Chori_Park_The_pine_forest_%C5%8Chorik%C5%8Den_Ch%C5%AB%C5%8D-ku_Fukuoka_20260427_172621.jpg",
          "credit": "Hirho",
          "license": "CC BY 4.0",
          "gps": {
            "lat": 33.58571,
            "lng": 130.37836
          }
        },
        {
          "title": "20260603 163429 Ōhori Park Loop Path in Ōhorikōen Chūō-ku Fukuoka",
          "description": "20260603 163429 Ōhori Park Loop Path in Ōhorikōen Chūō-ku Fukuoka",
          "url": "https://upload.wikimedia.org/wikipedia/commons/thumb/2/24/20260603_163429_%C5%8Chori_Park_Loop_Path_in_%C5%8Chorik%C5%8Den_Ch%C5%AB%C5%8D-ku_Fukuoka.png/960px-20260603_163429_%C5%8Chori_Park_Loop_Path_in_%C5%8Chorik%C5%8Den_Ch%C5%AB%C5%8D-ku_Fukuoka.png",
          "sourceUrl": "https://commons.wikimedia.org/wiki/File:20260603_163429_%C5%8Chori_Park_Loop_Path_in_%C5%8Chorik%C5%8Den_Ch%C5%AB%C5%8D-ku_Fukuoka.png",
          "credit": "Hirho",
          "license": "CC BY 4.0",
          "gps": {
            "lat": 33.58532,
            "lng": 130.37895
          }
        }
      ]
    },
    {
      "fraction": 0.2,
      "point": {
        "lat": 33.588712324864495,
        "lng": 130.3774080410362,
        "ele": -5.1
      },
      "stations": [
        {
          "name": "大濠公園",
          "prefecture": "福岡県",
          "line": "福岡市空港線",
          "x": 130.378784,
          "y": 33.589957,
          "postal": "8100074",
          "distance": "190m",
          "prev": "唐人町",
          "next": "赤坂"
        },
        {
          "name": "唐人町",
          "prefecture": "福岡県",
          "line": "福岡市空港線",
          "x": 130.370451,
          "y": 33.590235,
          "postal": "8100063",
          "distance": "670m",
          "prev": "西新",
          "next": "大濠公園"
        },
        {
          "name": "六本松",
          "prefecture": "福岡県",
          "line": "福岡市七隈線",
          "x": 130.377287,
          "y": 33.577678,
          "postal": "8100044",
          "distance": "1230m",
          "prev": "別府",
          "next": "桜坂"
        }
      ],
      "photos": [
        {
          "title": "Ohori Park 20150927-1",
          "description": "大濠公園の景色",
          "url": "https://upload.wikimedia.org/wikipedia/commons/thumb/5/54/Ohori_Park_20150927-1.JPG/960px-Ohori_Park_20150927-1.JPG",
          "sourceUrl": "https://commons.wikimedia.org/wiki/File:Ohori_Park_20150927-1.JPG",
          "credit": "そらみみ (Soramimi)",
          "license": "CC BY-SA 4.0",
          "gps": {
            "lat": 33.589006,
            "lng": 130.377106
          }
        },
        {
          "title": "View of Kangetsubashi Bridge in Ohori Park",
          "description": "大濠公園・観月橋の遠景",
          "url": "https://upload.wikimedia.org/wikipedia/commons/thumb/2/2c/View_of_Kangetsubashi_Bridge_in_Ohori_Park.JPG/960px-View_of_Kangetsubashi_Bridge_in_Ohori_Park.JPG",
          "sourceUrl": "https://commons.wikimedia.org/wiki/File:View_of_Kangetsubashi_Bridge_in_Ohori_Park.JPG",
          "credit": "そらみみ (Soramimi)",
          "license": "CC BY-SA 4.0",
          "gps": {
            "lat": 33.588978,
            "lng": 130.377129
          }
        },
        {
          "title": "Tulip flowers in Ohori Park",
          "description": "大濠公園のチューリップ",
          "url": "https://upload.wikimedia.org/wikipedia/commons/thumb/d/d0/Tulip_flowers_in_Ohori_Park.JPG/960px-Tulip_flowers_in_Ohori_Park.JPG",
          "sourceUrl": "https://commons.wikimedia.org/wiki/File:Tulip_flowers_in_Ohori_Park.JPG",
          "credit": "そらみみ (Soramimi)",
          "license": "CC BY-SA 4.0",
          "gps": {
            "lat": 33.588508,
            "lng": 130.377533
          }
        },
        {
          "title": "Ohori Park 20170404",
          "description": "大濠公園の様子",
          "url": "https://upload.wikimedia.org/wikipedia/commons/thumb/8/84/Ohori_Park_20170404.jpg/960px-Ohori_Park_20170404.jpg",
          "sourceUrl": "https://commons.wikimedia.org/wiki/File:Ohori_Park_20170404.jpg",
          "credit": "そらみみ",
          "license": "CC BY-SA 4.0",
          "gps": {
            "lat": 33.588958,
            "lng": 130.377153
          }
        },
        {
          "title": "Ohori Park 20170623-2",
          "description": "大濠公園の景色",
          "url": "https://upload.wikimedia.org/wikipedia/commons/thumb/a/ae/Ohori_Park_20170623-2.jpg/960px-Ohori_Park_20170623-2.jpg",
          "sourceUrl": "https://commons.wikimedia.org/wiki/File:Ohori_Park_20170623-2.jpg",
          "credit": "そらみみ",
          "license": "CC BY-SA 4.0",
          "gps": {
            "lat": 33.589022,
            "lng": 130.377456
          }
        },
        {
          "title": "Ohori Park at dusk 20170930-1",
          "description": "大濠公園の景色",
          "url": "https://upload.wikimedia.org/wikipedia/commons/thumb/1/10/Ohori_Park_at_dusk_20170930-1.jpg/960px-Ohori_Park_at_dusk_20170930-1.jpg",
          "sourceUrl": "https://commons.wikimedia.org/wiki/File:Ohori_Park_at_dusk_20170930-1.jpg",
          "credit": "そらみみ",
          "license": "CC BY-SA 4.0",
          "gps": {
            "lat": 33.588975,
            "lng": 130.377122
          }
        },
        {
          "title": "Ohori Park at dusk 20170930-2",
          "description": "大濠公園の景色",
          "url": "https://upload.wikimedia.org/wikipedia/commons/thumb/8/85/Ohori_Park_at_dusk_20170930-2.jpg/960px-Ohori_Park_at_dusk_20170930-2.jpg",
          "sourceUrl": "https://commons.wikimedia.org/wiki/File:Ohori_Park_at_dusk_20170930-2.jpg",
          "credit": "そらみみ",
          "license": "CC BY-SA 4.0",
          "gps": {
            "lat": 33.58865,
            "lng": 130.377333
          }
        },
        {
          "title": "Ohori Park at dusk 20170930-3",
          "description": "大濠公園の景色",
          "url": "https://upload.wikimedia.org/wikipedia/commons/thumb/7/7e/Ohori_Park_at_dusk_20170930-3.jpg/960px-Ohori_Park_at_dusk_20170930-3.jpg",
          "sourceUrl": "https://commons.wikimedia.org/wiki/File:Ohori_Park_at_dusk_20170930-3.jpg",
          "credit": "そらみみ",
          "license": "CC BY-SA 4.0",
          "gps": {
            "lat": 33.588325,
            "lng": 130.377456
          }
        }
      ]
    },
    {
      "fraction": 0.4,
      "point": {
        "lat": 33.588346373306955,
        "lng": 130.3739032234424,
        "ele": 0.4
      },
      "stations": [
        {
          "name": "唐人町",
          "prefecture": "福岡県",
          "line": "福岡市空港線",
          "x": 130.370451,
          "y": 33.590235,
          "postal": "8100063",
          "distance": "380m",
          "prev": "西新",
          "next": "大濠公園"
        },
        {
          "name": "大濠公園",
          "prefecture": "福岡県",
          "line": "福岡市空港線",
          "x": 130.378784,
          "y": 33.589957,
          "postal": "8100074",
          "distance": "490m",
          "prev": "唐人町",
          "next": "赤坂"
        },
        {
          "name": "六本松",
          "prefecture": "福岡県",
          "line": "福岡市七隈線",
          "x": 130.377287,
          "y": 33.577678,
          "postal": "8100044",
          "distance": "1230m",
          "prev": "別府",
          "next": "桜坂"
        }
      ],
      "photos": [
        {
          "title": "Nishi-nippon Ohori Fireworks Festival 20160801-2",
          "description": "第54回西日本大濠花火大会",
          "url": "https://upload.wikimedia.org/wikipedia/commons/thumb/4/42/Nishi-nippon_Ohori_Fireworks_Festival_20160801-2.jpg/960px-Nishi-nippon_Ohori_Fireworks_Festival_20160801-2.jpg",
          "sourceUrl": "https://commons.wikimedia.org/wiki/File:Nishi-nippon_Ohori_Fireworks_Festival_20160801-2.jpg",
          "credit": "そらみみ (Soramimi)",
          "license": "CC BY-SA 4.0",
          "gps": {
            "lat": 33.588561,
            "lng": 130.374114
          }
        },
        {
          "title": "Ohori Park Maizuru Bridge",
          "description": "Ōhori Park Maizuru Bridge, Chuo Ward, Fukuoka City, Fukuoka, Japan.",
          "url": "https://upload.wikimedia.org/wikipedia/commons/thumb/1/1c/Ohori_Park_Maizuru_Bridge.jpg/960px-Ohori_Park_Maizuru_Bridge.jpg",
          "sourceUrl": "https://commons.wikimedia.org/wiki/File:Ohori_Park_Maizuru_Bridge.jpg",
          "credit": "Muyo",
          "license": "CC BY-SA 4.0",
          "gps": {
            "lat": 33.588386,
            "lng": 130.373941
          }
        },
        {
          "title": "Maizurubashi Bridge in Ohori Park",
          "description": "大濠公園・南側より望む舞鶴橋",
          "url": "https://upload.wikimedia.org/wikipedia/commons/thumb/7/77/Maizurubashi_Bridge_in_Ohori_Park.jpg/960px-Maizurubashi_Bridge_in_Ohori_Park.jpg",
          "sourceUrl": "https://commons.wikimedia.org/wiki/File:Maizurubashi_Bridge_in_Ohori_Park.jpg",
          "credit": "そらみみ",
          "license": "CC BY-SA 4.0",
          "gps": {
            "lat": 33.588189,
            "lng": 130.373725
          }
        },
        {
          "title": "View near Ohori Police Box of Chuo Police Station",
          "description": "中央警察署大濠連絡派出所付近の大濠公園",
          "url": "https://upload.wikimedia.org/wikipedia/commons/thumb/8/8f/View_near_Ohori_Police_Box_of_Chuo_Police_Station.jpg/960px-View_near_Ohori_Police_Box_of_Chuo_Police_Station.jpg",
          "sourceUrl": "https://commons.wikimedia.org/wiki/File:View_near_Ohori_Police_Box_of_Chuo_Police_Station.jpg",
          "credit": "そらみみ",
          "license": "CC BY-SA 4.0",
          "gps": {
            "lat": 33.588158,
            "lng": 130.373794
          }
        },
        {
          "title": "Kuromongawa River from Maizurubashi Bridge in Ohori Park",
          "description": "大濠公園の舞鶴橋より望む黒門川(下流側)",
          "url": "https://upload.wikimedia.org/wikipedia/commons/thumb/4/47/Kuromongawa_River_from_Maizurubashi_Bridge_in_Ohori_Park.jpg/960px-Kuromongawa_River_from_Maizurubashi_Bridge_in_Ohori_Park.jpg",
          "sourceUrl": "https://commons.wikimedia.org/wiki/File:Kuromongawa_River_from_Maizurubashi_Bridge_in_Ohori_Park.jpg",
          "credit": "そらみみ",
          "license": "CC BY-SA 4.0",
          "gps": {
            "lat": 33.588403,
            "lng": 130.373844
          }
        },
        {
          "title": "View of Consulate of the United States in Fukuoka from Ohori Park",
          "description": "大濠公園より望む在福岡米国領事館",
          "url": "https://upload.wikimedia.org/wikipedia/commons/thumb/3/33/View_of_Consulate_of_the_United_States_in_Fukuoka_from_Ohori_Park.jpg/960px-View_of_Consulate_of_the_United_States_in_Fukuoka_from_Ohori_Park.jpg",
          "sourceUrl": "https://commons.wikimedia.org/wiki/File:View_of_Consulate_of_the_United_States_in_Fukuoka_from_Ohori_Park.jpg",
          "credit": "そらみみ",
          "license": "CC BY-SA 4.0",
          "gps": {
            "lat": 33.588256,
            "lng": 130.373792
          }
        },
        {
          "title": "Kangetsubashi Bridge in Ohori Park 3",
          "description": "大濠公園の観月橋",
          "url": "https://upload.wikimedia.org/wikipedia/commons/thumb/2/28/Kangetsubashi_Bridge_in_Ohori_Park_3.jpg/960px-Kangetsubashi_Bridge_in_Ohori_Park_3.jpg",
          "sourceUrl": "https://commons.wikimedia.org/wiki/File:Kangetsubashi_Bridge_in_Ohori_Park_3.jpg",
          "credit": "そらみみ",
          "license": "CC BY-SA 4.0",
          "gps": {
            "lat": 33.588661,
            "lng": 130.374192
          }
        },
        {
          "title": "Kangetsubashi Bridge and Ukimido Hall from Maizurubashi Bridge",
          "description": "大濠公園の舞鶴橋より望む浮見堂と観月橋",
          "url": "https://upload.wikimedia.org/wikipedia/commons/thumb/4/4c/Kangetsubashi_Bridge_and_Ukimido_Hall_from_Maizurubashi_Bridge.jpg/960px-Kangetsubashi_Bridge_and_Ukimido_Hall_from_Maizurubashi_Bridge.jpg",
          "sourceUrl": "https://commons.wikimedia.org/wiki/File:Kangetsubashi_Bridge_and_Ukimido_Hall_from_Maizurubashi_Bridge.jpg",
          "credit": "そらみみ",
          "license": "CC BY-SA 4.0",
          "gps": {
            "lat": 33.588283,
            "lng": 130.373886
          }
        }
      ]
    },
    {
      "fraction": 0.6,
      "point": {
        "lat": 33.58500001383415,
        "lng": 130.3740084625425,
        "ele": 1.9
      },
      "stations": [
        {
          "name": "唐人町",
          "prefecture": "福岡県",
          "line": "福岡市空港線",
          "x": 130.370451,
          "y": 33.590235,
          "postal": "8100063",
          "distance": "670m",
          "prev": "西新",
          "next": "大濠公園"
        },
        {
          "name": "大濠公園",
          "prefecture": "福岡県",
          "line": "福岡市空港線",
          "x": 130.378784,
          "y": 33.589957,
          "postal": "8100074",
          "distance": "710m",
          "prev": "唐人町",
          "next": "赤坂"
        },
        {
          "name": "六本松",
          "prefecture": "福岡県",
          "line": "福岡市七隈線",
          "x": 130.377287,
          "y": 33.577678,
          "postal": "8100044",
          "distance": "870m",
          "prev": "別府",
          "next": "桜坂"
        }
      ],
      "photos": [
        {
          "title": "View of Kamoshima Island and Kangetsubashi Bridge from Ayameshima Island of Ohori Park",
          "description": "菖蒲島より望む大濠公園(鴨島・能楽堂・観月橋方面)",
          "url": "https://upload.wikimedia.org/wikipedia/commons/thumb/f/f0/View_of_Kamoshima_Island_and_Kangetsubashi_Bridge_from_Ayameshima_Island_of_Ohori_Park.JPG/960px-View_of_Kamoshima_Island_and_Kangetsubashi_Bridge_from_Ayameshima_Island_of_Ohori_Park.JPG",
          "sourceUrl": "https://commons.wikimedia.org/wiki/File:View_of_Kamoshima_Island_and_Kangetsubashi_Bridge_from_Ayameshima_Island_of_Ohori_Park.JPG",
          "credit": "そらみみ (Soramimi)",
          "license": "CC BY-SA 4.0",
          "gps": {
            "lat": 33.584389,
            "lng": 130.375533
          }
        },
        {
          "title": "Ayameshima Island in Ohori Park",
          "description": "大濠公園の菖蒲島",
          "url": "https://upload.wikimedia.org/wikipedia/commons/thumb/d/d1/Ayameshima_Island_in_Ohori_Park.JPG/960px-Ayameshima_Island_in_Ohori_Park.JPG",
          "sourceUrl": "https://commons.wikimedia.org/wiki/File:Ayameshima_Island_in_Ohori_Park.JPG",
          "credit": "そらみみ (Soramimi)",
          "license": "CC BY-SA 4.0",
          "gps": {
            "lat": 33.584253,
            "lng": 130.37555
          }
        },
        {
          "title": "View from Satsukibashi Bridge of Ohori Park",
          "description": "さつき橋より望む大濠公園(NHK福岡放送局方面)",
          "url": "https://upload.wikimedia.org/wikipedia/commons/thumb/a/a5/View_from_Satsukibashi_Bridge_of_Ohori_Park.JPG/960px-View_from_Satsukibashi_Bridge_of_Ohori_Park.JPG",
          "sourceUrl": "https://commons.wikimedia.org/wiki/File:View_from_Satsukibashi_Bridge_of_Ohori_Park.JPG",
          "credit": "そらみみ (Soramimi)",
          "license": "CC BY-SA 4.0",
          "gps": {
            "lat": 33.58405,
            "lng": 130.375367
          }
        },
        {
          "title": "View of Kamoshima Island from Satsukibashi Bridge of Ohori Park",
          "description": "菖蒲島より望む大濠公園(鴨島・観月橋方面)",
          "url": "https://upload.wikimedia.org/wikipedia/commons/thumb/9/97/View_of_Kamoshima_Island_from_Satsukibashi_Bridge_of_Ohori_Park.JPG/960px-View_of_Kamoshima_Island_from_Satsukibashi_Bridge_of_Ohori_Park.JPG",
          "sourceUrl": "https://commons.wikimedia.org/wiki/File:View_of_Kamoshima_Island_from_Satsukibashi_Bridge_of_Ohori_Park.JPG",
          "credit": "そらみみ (Soramimi)",
          "license": "CC BY-SA 4.0",
          "gps": {
            "lat": 33.583922,
            "lng": 130.375167
          }
        },
        {
          "title": "View of from southwest side of Ohori Park (east)",
          "description": "南西側より望む大濠公園(鴨島方面)",
          "url": "https://upload.wikimedia.org/wikipedia/commons/thumb/6/68/View_of_from_southwest_side_of_Ohori_Park_%28east%29.JPG/960px-View_of_from_southwest_side_of_Ohori_Park_%28east%29.JPG",
          "sourceUrl": "https://commons.wikimedia.org/wiki/File:View_of_from_southwest_side_of_Ohori_Park_(east).JPG",
          "credit": "そらみみ (Soramimi)",
          "license": "CC BY-SA 4.0",
          "gps": {
            "lat": 33.584175,
            "lng": 130.374419
          }
        },
        {
          "title": "View of from southwest side of Ohori Park (north)",
          "description": "南西側より望む大濠公園(観月橋方面)",
          "url": "https://upload.wikimedia.org/wikipedia/commons/thumb/6/60/View_of_from_southwest_side_of_Ohori_Park_%28north%29.JPG/960px-View_of_from_southwest_side_of_Ohori_Park_%28north%29.JPG",
          "sourceUrl": "https://commons.wikimedia.org/wiki/File:View_of_from_southwest_side_of_Ohori_Park_(north).JPG",
          "credit": "そらみみ (Soramimi)",
          "license": "CC BY-SA 4.0",
          "gps": {
            "lat": 33.584217,
            "lng": 130.374375
          }
        },
        {
          "title": "View of Satsukibashi Bridge of Ohori Park from west side",
          "description": "大濠公園のさつき橋",
          "url": "https://upload.wikimedia.org/wikipedia/commons/thumb/b/ba/View_of_Satsukibashi_Bridge_of_Ohori_Park_from_west_side.JPG/960px-View_of_Satsukibashi_Bridge_of_Ohori_Park_from_west_side.JPG",
          "sourceUrl": "https://commons.wikimedia.org/wiki/File:View_of_Satsukibashi_Bridge_of_Ohori_Park_from_west_side.JPG",
          "credit": "そらみみ (Soramimi)",
          "license": "CC BY-SA 4.0",
          "gps": {
            "lat": 33.584217,
            "lng": 130.374375
          }
        },
        {
          "title": "Ayameshima Island of Ohori Park",
          "description": "大濠公園・菖蒲島の遠景",
          "url": "https://upload.wikimedia.org/wikipedia/commons/thumb/0/0f/Ayameshima_Island_of_Ohori_Park.JPG/960px-Ayameshima_Island_of_Ohori_Park.JPG",
          "sourceUrl": "https://commons.wikimedia.org/wiki/File:Ayameshima_Island_of_Ohori_Park.JPG",
          "credit": "そらみみ (Soramimi)",
          "license": "CC BY-SA 4.0",
          "gps": {
            "lat": 33.584178,
            "lng": 130.374358
          }
        }
      ]
    },
    {
      "fraction": 0.8,
      "point": {
        "lat": 33.58290026750772,
        "lng": 130.37691567507716,
        "ele": 4.4
      },
      "stations": [
        {
          "name": "六本松",
          "prefecture": "福岡県",
          "line": "福岡市七隈線",
          "x": 130.377287,
          "y": 33.577678,
          "postal": "8100044",
          "distance": "580m",
          "prev": "別府",
          "next": "桜坂"
        },
        {
          "name": "大濠公園",
          "prefecture": "福岡県",
          "line": "福岡市空港線",
          "x": 130.378784,
          "y": 33.589957,
          "postal": "8100074",
          "distance": "800m",
          "prev": "唐人町",
          "next": "赤坂"
        },
        {
          "name": "唐人町",
          "prefecture": "福岡県",
          "line": "福岡市空港線",
          "x": 130.370451,
          "y": 33.590235,
          "postal": "8100063",
          "distance": "1010m",
          "prev": "西新",
          "next": "大濠公園"
        }
      ],
      "photos": [
        {
          "title": "Ohori Park 20170505-5",
          "description": "南岸より望む大濠公園",
          "url": "https://upload.wikimedia.org/wikipedia/commons/thumb/b/b9/Ohori_Park_20170505-5.jpg/960px-Ohori_Park_20170505-5.jpg",
          "sourceUrl": "https://commons.wikimedia.org/wiki/File:Ohori_Park_20170505-5.jpg",
          "credit": "そらみみ",
          "license": "CC BY-SA 4.0",
          "gps": {
            "lat": 33.582942,
            "lng": 130.377153
          }
        },
        {
          "title": "Fukuoka Budōkan The NW side Ōhori 1-chōme Chūō-ku Fukuoka 20250912 155412",
          "description": "Fukuoka Budōkan: The northwest side (Address: 1-1, Ōhori 1-chōme, Chūō-ku, Fukuoka-shi 810-0052, Japan)",
          "url": "https://upload.wikimedia.org/wikipedia/commons/thumb/9/96/Fukuoka_Bud%C5%8Dkan_The_NW_side_%C5%8Chori_1-ch%C5%8Dme_Ch%C5%AB%C5%8D-ku_Fukuoka_20250912_155412.jpg/960px-Fukuoka_Bud%C5%8Dkan_The_NW_side_%C5%8Chori_1-ch%C5%8Dme_Ch%C5%AB%C5%8D-ku_Fukuoka_20250912_155412.jpg",
          "sourceUrl": "https://commons.wikimedia.org/wiki/File:Fukuoka_Bud%C5%8Dkan_The_NW_side_%C5%8Chori_1-ch%C5%8Dme_Ch%C5%AB%C5%8D-ku_Fukuoka_20250912_155412.jpg",
          "credit": "Hirho",
          "license": "CC BY 4.0",
          "gps": {
            "lat": 33.58272,
            "lng": 130.37732
          }
        },
        {
          "title": "Fukuoka Budōkan The areaway on the N side Ōhori 1-chōme Chūō-ku Fukuoka 20250912 155506",
          "description": "Fukuoka Budōkan: The areaway on the north side (Address: 1-1, Ōhori 1-chōme, Chūō-ku, Fukuoka-shi 810-0052, Japan)",
          "url": "https://upload.wikimedia.org/wikipedia/commons/thumb/b/bd/Fukuoka_Bud%C5%8Dkan_The_areaway_on_the_N_side_%C5%8Chori_1-ch%C5%8Dme_Ch%C5%AB%C5%8D-ku_Fukuoka_20250912_155506.jpg/960px-Fukuoka_Bud%C5%8Dkan_The_areaway_on_the_N_side_%C5%8Chori_1-ch%C5%8Dme_Ch%C5%AB%C5%8D-ku_Fukuoka_20250912_155506.jpg",
          "sourceUrl": "https://commons.wikimedia.org/wiki/File:Fukuoka_Bud%C5%8Dkan_The_areaway_on_the_N_side_%C5%8Chori_1-ch%C5%8Dme_Ch%C5%AB%C5%8D-ku_Fukuoka_20250912_155506.jpg",
          "credit": "Hirho",
          "license": "CC BY 4.0",
          "gps": {
            "lat": 33.58265,
            "lng": 130.37742
          }
        },
        {
          "title": "Ōhori Terrace The façade Ōhori-kōen Chūō-ku Fukuoka 20250912 153742",
          "description": "Ōhori Terrace: The façade (Address: 1-9, Ōhori-kōen, Chūō-ku, Fukuoka-shi 810-0051 , Japan)",
          "url": "https://upload.wikimedia.org/wikipedia/commons/thumb/7/7c/%C5%8Chori_Terrace_The_fa%C3%A7ade_%C5%8Chori-k%C5%8Den_Ch%C5%AB%C5%8D-ku_Fukuoka_20250912_153742.jpg/960px-%C5%8Chori_Terrace_The_fa%C3%A7ade_%C5%8Chori-k%C5%8Den_Ch%C5%AB%C5%8D-ku_Fukuoka_20250912_153742.jpg",
          "sourceUrl": "https://commons.wikimedia.org/wiki/File:%C5%8Chori_Terrace_The_fa%C3%A7ade_%C5%8Chori-k%C5%8Den_Ch%C5%AB%C5%8D-ku_Fukuoka_20250912_153742.jpg",
          "credit": "Hirho",
          "license": "CC BY 4.0",
          "gps": {
            "lat": 33.58297,
            "lng": 130.37696
          }
        },
        {
          "title": "Ōhori Terrace The NW side Ōhori-kōen Chūō-ku Fukuoka 20250912 153842",
          "description": "Ōhori Terrace: The northwest side (Address: 1-9, Ōhori-kōen, Chūō-ku, Fukuoka-shi 810-0051, Japan)",
          "url": "https://upload.wikimedia.org/wikipedia/commons/thumb/5/5c/%C5%8Chori_Terrace_The_NW_side_%C5%8Chori-k%C5%8Den_Ch%C5%AB%C5%8D-ku_Fukuoka_20250912_153842.jpg/960px-%C5%8Chori_Terrace_The_NW_side_%C5%8Chori-k%C5%8Den_Ch%C5%AB%C5%8D-ku_Fukuoka_20250912_153842.jpg",
          "sourceUrl": "https://commons.wikimedia.org/wiki/File:%C5%8Chori_Terrace_The_NW_side_%C5%8Chori-k%C5%8Den_Ch%C5%AB%C5%8D-ku_Fukuoka_20250912_153842.jpg",
          "credit": "Hirho",
          "license": "CC BY 4.0",
          "gps": {
            "lat": 33.58281,
            "lng": 130.37684
          }
        },
        {
          "title": "Ōhori Terrace The NW side Ōhori-kōen Chūō-ku Fukuoka 20250912 153916",
          "description": "Ōhori Terrace: The northwest side (Address: 1-9, Ōhori-kōen, Chūō-ku, Fukuoka-shi 810-0051, Japan)",
          "url": "https://upload.wikimedia.org/wikipedia/commons/thumb/d/d9/%C5%8Chori_Terrace_The_NW_side_%C5%8Chori-k%C5%8Den_Ch%C5%AB%C5%8D-ku_Fukuoka_20250912_153916.jpg/960px-%C5%8Chori_Terrace_The_NW_side_%C5%8Chori-k%C5%8Den_Ch%C5%AB%C5%8D-ku_Fukuoka_20250912_153916.jpg",
          "sourceUrl": "https://commons.wikimedia.org/wiki/File:%C5%8Chori_Terrace_The_NW_side_%C5%8Chori-k%C5%8Den_Ch%C5%AB%C5%8D-ku_Fukuoka_20250912_153916.jpg",
          "credit": "Hirho",
          "license": "CC BY 4.0",
          "gps": {
            "lat": 33.58284,
            "lng": 130.37679
          }
        },
        {
          "title": "Ōhori Terrace The entrance on the NW side Ōhori-kōen Chūō-ku Fukuoka 20250912 153952",
          "description": "Ōhori Terrace: The entrance on the northwest side (Address: 1-9, Ōhori-kōen, Chūō-ku, Fukuoka-shi 810-0051, Japan)",
          "url": "https://upload.wikimedia.org/wikipedia/commons/thumb/4/49/%C5%8Chori_Terrace_The_entrance_on_the_NW_side_%C5%8Chori-k%C5%8Den_Ch%C5%AB%C5%8D-ku_Fukuoka_20250912_153952.jpg/960px-%C5%8Chori_Terrace_The_entrance_on_the_NW_side_%C5%8Chori-k%C5%8Den_Ch%C5%AB%C5%8D-ku_Fukuoka_20250912_153952.jpg",
          "sourceUrl": "https://commons.wikimedia.org/wiki/File:%C5%8Chori_Terrace_The_entrance_on_the_NW_side_%C5%8Chori-k%C5%8Den_Ch%C5%AB%C5%8D-ku_Fukuoka_20250912_153952.jpg",
          "credit": "Hirho",
          "license": "CC BY 4.0",
          "gps": {
            "lat": 33.5828,
            "lng": 130.37687
          }
        },
        {
          "title": "Ōhori Terrace The exit on the NE side Ōhori-kōen Chūō-ku Fukuoka 20250912 154106",
          "description": "Ōhori Terrace: The exit on the northeast side (Address: 1-9, Ōhori-kōen, Chūō-ku, Fukuoka-shi 810-0051, Japan)",
          "url": "https://upload.wikimedia.org/wikipedia/commons/thumb/5/58/%C5%8Chori_Terrace_The_exit_on_the_NE_side_%C5%8Chori-k%C5%8Den_Ch%C5%AB%C5%8D-ku_Fukuoka_20250912_154106.jpg/960px-%C5%8Chori_Terrace_The_exit_on_the_NE_side_%C5%8Chori-k%C5%8Den_Ch%C5%AB%C5%8D-ku_Fukuoka_20250912_154106.jpg",
          "sourceUrl": "https://commons.wikimedia.org/wiki/File:%C5%8Chori_Terrace_The_exit_on_the_NE_side_%C5%8Chori-k%C5%8Den_Ch%C5%AB%C5%8D-ku_Fukuoka_20250912_154106.jpg",
          "credit": "Hirho",
          "license": "CC BY 4.0",
          "gps": {
            "lat": 33.5828,
            "lng": 130.37714
          }
        }
      ]
    }
  ],
  "reviewStatus": "needs_review"
}
