{
  "slug": "yoron-loop",
  "spot": {
    "slug": "yoron-loop",
    "name": "与論島一周コース",
    "prefecture": "鹿児島県",
    "city": "大島郡与論町",
    "access": "与論港からスタート。与論空港からも車で約5分です。",
    "course_type": "loop",
    "distance_m": 22867,
    "elevation_gain_m": 261,
    "hasGpx": true,
    "hasGuide": false,
    "pointCount": 4807,
    "gpxDistanceM": 22867,
    "distanceDifferencePct": 0,
    "closureGapM": 0,
    "hasGpxElevation": true,
    "detectedCourseType": "loop",
    "issues": []
  },
  "collectedAt": "2026-07-13T09:23:40.216Z",
  "sources": {
    "stations": "https://express.heartrails.com/api.html",
    "photos": "https://commons.wikimedia.org/wiki/Commons:API/MediaWiki",
    "photoSearch": "https://commons.wikimedia.org/wiki/Commons:API/MediaWiki"
  },
  "samples": [
    {
      "fraction": 0,
      "point": {
        "lat": 27.048175,
        "lng": 128.413813,
        "ele": 13.7
      },
      "stations": [],
      "photos": [
        {
          "title": "Yoron Port Kagoshima Kagoshima JAPAN",
          "description": "与論港",
          "url": "https://upload.wikimedia.org/wikipedia/commons/thumb/2/2e/Yoron_Port_Kagoshima_Kagoshima_JAPAN.jpg/960px-Yoron_Port_Kagoshima_Kagoshima_JAPAN.jpg",
          "sourceUrl": "https://commons.wikimedia.org/wiki/File:Yoron_Port_Kagoshima_Kagoshima_JAPAN.jpg",
          "credit": "Rsa",
          "license": "CC BY-SA 3.0",
          "gps": {
            "lat": 27.034966,
            "lng": 128.401648
          }
        },
        {
          "title": "Yoron PRICIA 0122",
          "description": "プリシアリゾート ヨロン 送迎バス",
          "url": "https://upload.wikimedia.org/wikipedia/commons/thumb/3/30/Yoron_PRICIA_0122.jpg/960px-Yoron_PRICIA_0122.jpg",
          "sourceUrl": "https://commons.wikimedia.org/wiki/File:Yoron_PRICIA_0122.jpg",
          "credit": "Rsa",
          "license": "CC BY-SA 3.0",
          "gps": {
            "lat": 27.036286,
            "lng": 128.401261
          }
        },
        {
          "title": "Welcome sign in Miyako",
          "description": "Welcome (Nmyachi んみゃーち) sign in Miyako, at Miyako Airport.",
          "url": "https://upload.wikimedia.org/wikipedia/commons/thumb/3/36/Welcome_sign_in_Miyako.jpg/960px-Welcome_sign_in_Miyako.jpg",
          "sourceUrl": "https://commons.wikimedia.org/wiki/File:Welcome_sign_in_Miyako.jpg",
          "credit": "Kzaral",
          "license": "CC BY 2.0",
          "gps": {
            "lat": 27.045044,
            "lng": 128.396239
          }
        },
        {
          "title": "プリシアリゾート",
          "description": "プリシアリゾート",
          "url": "https://upload.wikimedia.org/wikipedia/commons/thumb/b/b6/%E3%83%97%E3%83%AA%E3%82%B7%E3%82%A2%E3%83%AA%E3%82%BE%E3%83%BC%E3%83%88.jpg/960px-%E3%83%97%E3%83%AA%E3%82%B7%E3%82%A2%E3%83%AA%E3%82%BE%E3%83%BC%E3%83%88.jpg",
          "sourceUrl": "https://commons.wikimedia.org/wiki/File:%E3%83%97%E3%83%AA%E3%82%B7%E3%82%A2%E3%83%AA%E3%82%BE%E3%83%BC%E3%83%88.jpg",
          "credit": "daipresents",
          "license": "CC BY 3.0",
          "gps": {
            "lat": 27.050859,
            "lng": 128.398993
          }
        },
        {
          "title": "プリシアリゾート2",
          "description": "プリシアリゾート",
          "url": "https://upload.wikimedia.org/wikipedia/commons/thumb/d/d8/%E3%83%97%E3%83%AA%E3%82%B7%E3%82%A2%E3%83%AA%E3%82%BE%E3%83%BC%E3%83%882.jpg/960px-%E3%83%97%E3%83%AA%E3%82%B7%E3%82%A2%E3%83%AA%E3%82%BE%E3%83%BC%E3%83%882.jpg",
          "sourceUrl": "https://commons.wikimedia.org/wiki/File:%E3%83%97%E3%83%AA%E3%82%B7%E3%82%A2%E3%83%AA%E3%82%BE%E3%83%BC%E3%83%882.jpg",
          "credit": "daipresents",
          "license": "CC BY 3.0",
          "gps": {
            "lat": 27.050744,
            "lng": 128.398993
          }
        },
        {
          "title": "プリシアリゾートプライベートビーチ",
          "description": "プリシアリゾートプライベートビーチ",
          "url": "https://upload.wikimedia.org/wikipedia/commons/thumb/2/29/%E3%83%97%E3%83%AA%E3%82%B7%E3%82%A2%E3%83%AA%E3%82%BE%E3%83%BC%E3%83%88%E3%83%97%E3%83%A9%E3%82%A4%E3%83%99%E3%83%BC%E3%83%88%E3%83%93%E3%83%BC%E3%83%81.jpg/960px-%E3%83%97%E3%83%AA%E3%82%B7%E3%82%A2%E3%83%AA%E3%82%BE%E3%83%BC%E3%83%88%E3%83%97%E3%83%A9%E3%82%A4%E3%83%99%E3%83%BC%E3%83%88%E3%83%93%E3%83%BC%E3%83%81.jpg",
          "sourceUrl": "https://commons.wikimedia.org/wiki/File:%E3%83%97%E3%83%AA%E3%82%B7%E3%82%A2%E3%83%AA%E3%82%BE%E3%83%BC%E3%83%88%E3%83%97%E3%83%A9%E3%82%A4%E3%83%99%E3%83%BC%E3%83%88%E3%83%93%E3%83%BC%E3%83%81.jpg",
          "credit": "daipresents",
          "license": "CC BY 3.0",
          "gps": {
            "lat": 27.050974,
            "lng": 128.398649
          }
        },
        {
          "title": "プリシアリゾートのバーベキューテラス - panoramio",
          "description": "プリシアリゾートのバーベキューテラス",
          "url": "https://upload.wikimedia.org/wikipedia/commons/thumb/f/f1/%E3%83%97%E3%83%AA%E3%82%B7%E3%82%A2%E3%83%AA%E3%82%BE%E3%83%BC%E3%83%88%E3%81%AE%E3%83%90%E3%83%BC%E3%83%99%E3%82%AD%E3%83%A5%E3%83%BC%E3%83%86%E3%83%A9%E3%82%B9_-_panoramio.jpg/960px-%E3%83%97%E3%83%AA%E3%82%B7%E3%82%A2%E3%83%AA%E3%82%BE%E3%83%BC%E3%83%88%E3%81%AE%E3%83%90%E3%83%BC%E3%83%99%E3%82%AD%E3%83%A5%E3%83%BC%E3%83%86%E3%83%A9%E3%82%B9_-_panoramio.jpg",
          "sourceUrl": "https://commons.wikimedia.org/wiki/File:%E3%83%97%E3%83%AA%E3%82%B7%E3%82%A2%E3%83%AA%E3%82%BE%E3%83%BC%E3%83%88%E3%81%AE%E3%83%90%E3%83%BC%E3%83%99%E3%82%AD%E3%83%A5%E3%83%BC%E3%83%86%E3%83%A9%E3%82%B9_-_panoramio.jpg",
          "credit": "daipresents",
          "license": "CC BY 3.0",
          "gps": {
            "lat": 27.05102,
            "lng": 128.398723
          }
        },
        {
          "title": "与論空港 - panoramio",
          "description": "与論空港",
          "url": "https://upload.wikimedia.org/wikipedia/commons/thumb/b/b5/%E4%B8%8E%E8%AB%96%E7%A9%BA%E6%B8%AF_-_panoramio.jpg/960px-%E4%B8%8E%E8%AB%96%E7%A9%BA%E6%B8%AF_-_panoramio.jpg",
          "sourceUrl": "https://commons.wikimedia.org/wiki/File:%E4%B8%8E%E8%AB%96%E7%A9%BA%E6%B8%AF_-_panoramio.jpg",
          "credit": "daipresents",
          "license": "CC BY 3.0",
          "gps": {
            "lat": 27.043488,
            "lng": 128.400143
          }
        }
      ]
    },
    {
      "fraction": 0.2,
      "point": {
        "lat": 27.04060563009779,
        "lng": 128.40007162935424,
        "ele": 19.7
      },
      "stations": [],
      "photos": [
        {
          "title": "Yoron Port Kagoshima Kagoshima JAPAN",
          "description": "与論港",
          "url": "https://upload.wikimedia.org/wikipedia/commons/thumb/2/2e/Yoron_Port_Kagoshima_Kagoshima_JAPAN.jpg/960px-Yoron_Port_Kagoshima_Kagoshima_JAPAN.jpg",
          "sourceUrl": "https://commons.wikimedia.org/wiki/File:Yoron_Port_Kagoshima_Kagoshima_JAPAN.jpg",
          "credit": "Rsa",
          "license": "CC BY-SA 3.0",
          "gps": {
            "lat": 27.034966,
            "lng": 128.401648
          }
        },
        {
          "title": "Yoron PRICIA 0122",
          "description": "プリシアリゾート ヨロン 送迎バス",
          "url": "https://upload.wikimedia.org/wikipedia/commons/thumb/3/30/Yoron_PRICIA_0122.jpg/960px-Yoron_PRICIA_0122.jpg",
          "sourceUrl": "https://commons.wikimedia.org/wiki/File:Yoron_PRICIA_0122.jpg",
          "credit": "Rsa",
          "license": "CC BY-SA 3.0",
          "gps": {
            "lat": 27.036286,
            "lng": 128.401261
          }
        },
        {
          "title": "Welcome sign in Miyako",
          "description": "Welcome (Nmyachi んみゃーち) sign in Miyako, at Miyako Airport.",
          "url": "https://upload.wikimedia.org/wikipedia/commons/thumb/3/36/Welcome_sign_in_Miyako.jpg/960px-Welcome_sign_in_Miyako.jpg",
          "sourceUrl": "https://commons.wikimedia.org/wiki/File:Welcome_sign_in_Miyako.jpg",
          "credit": "Kzaral",
          "license": "CC BY 2.0",
          "gps": {
            "lat": 27.045044,
            "lng": 128.396239
          }
        },
        {
          "title": "プリシアリゾート",
          "description": "プリシアリゾート",
          "url": "https://upload.wikimedia.org/wikipedia/commons/thumb/b/b6/%E3%83%97%E3%83%AA%E3%82%B7%E3%82%A2%E3%83%AA%E3%82%BE%E3%83%BC%E3%83%88.jpg/960px-%E3%83%97%E3%83%AA%E3%82%B7%E3%82%A2%E3%83%AA%E3%82%BE%E3%83%BC%E3%83%88.jpg",
          "sourceUrl": "https://commons.wikimedia.org/wiki/File:%E3%83%97%E3%83%AA%E3%82%B7%E3%82%A2%E3%83%AA%E3%82%BE%E3%83%BC%E3%83%88.jpg",
          "credit": "daipresents",
          "license": "CC BY 3.0",
          "gps": {
            "lat": 27.050859,
            "lng": 128.398993
          }
        },
        {
          "title": "プリシアリゾート2",
          "description": "プリシアリゾート",
          "url": "https://upload.wikimedia.org/wikipedia/commons/thumb/d/d8/%E3%83%97%E3%83%AA%E3%82%B7%E3%82%A2%E3%83%AA%E3%82%BE%E3%83%BC%E3%83%882.jpg/960px-%E3%83%97%E3%83%AA%E3%82%B7%E3%82%A2%E3%83%AA%E3%82%BE%E3%83%BC%E3%83%882.jpg",
          "sourceUrl": "https://commons.wikimedia.org/wiki/File:%E3%83%97%E3%83%AA%E3%82%B7%E3%82%A2%E3%83%AA%E3%82%BE%E3%83%BC%E3%83%882.jpg",
          "credit": "daipresents",
          "license": "CC BY 3.0",
          "gps": {
            "lat": 27.050744,
            "lng": 128.398993
          }
        },
        {
          "title": "プリシアリゾートプライベートビーチ",
          "description": "プリシアリゾートプライベートビーチ",
          "url": "https://upload.wikimedia.org/wikipedia/commons/thumb/2/29/%E3%83%97%E3%83%AA%E3%82%B7%E3%82%A2%E3%83%AA%E3%82%BE%E3%83%BC%E3%83%88%E3%83%97%E3%83%A9%E3%82%A4%E3%83%99%E3%83%BC%E3%83%88%E3%83%93%E3%83%BC%E3%83%81.jpg/960px-%E3%83%97%E3%83%AA%E3%82%B7%E3%82%A2%E3%83%AA%E3%82%BE%E3%83%BC%E3%83%88%E3%83%97%E3%83%A9%E3%82%A4%E3%83%99%E3%83%BC%E3%83%88%E3%83%93%E3%83%BC%E3%83%81.jpg",
          "sourceUrl": "https://commons.wikimedia.org/wiki/File:%E3%83%97%E3%83%AA%E3%82%B7%E3%82%A2%E3%83%AA%E3%82%BE%E3%83%BC%E3%83%88%E3%83%97%E3%83%A9%E3%82%A4%E3%83%99%E3%83%BC%E3%83%88%E3%83%93%E3%83%BC%E3%83%81.jpg",
          "credit": "daipresents",
          "license": "CC BY 3.0",
          "gps": {
            "lat": 27.050974,
            "lng": 128.398649
          }
        },
        {
          "title": "プリシアリゾートのバーベキューテラス - panoramio",
          "description": "プリシアリゾートのバーベキューテラス",
          "url": "https://upload.wikimedia.org/wikipedia/commons/thumb/f/f1/%E3%83%97%E3%83%AA%E3%82%B7%E3%82%A2%E3%83%AA%E3%82%BE%E3%83%BC%E3%83%88%E3%81%AE%E3%83%90%E3%83%BC%E3%83%99%E3%82%AD%E3%83%A5%E3%83%BC%E3%83%86%E3%83%A9%E3%82%B9_-_panoramio.jpg/960px-%E3%83%97%E3%83%AA%E3%82%B7%E3%82%A2%E3%83%AA%E3%82%BE%E3%83%BC%E3%83%88%E3%81%AE%E3%83%90%E3%83%BC%E3%83%99%E3%82%AD%E3%83%A5%E3%83%BC%E3%83%86%E3%83%A9%E3%82%B9_-_panoramio.jpg",
          "sourceUrl": "https://commons.wikimedia.org/wiki/File:%E3%83%97%E3%83%AA%E3%82%B7%E3%82%A2%E3%83%AA%E3%82%BE%E3%83%BC%E3%83%88%E3%81%AE%E3%83%90%E3%83%BC%E3%83%99%E3%82%AD%E3%83%A5%E3%83%BC%E3%83%86%E3%83%A9%E3%82%B9_-_panoramio.jpg",
          "credit": "daipresents",
          "license": "CC BY 3.0",
          "gps": {
            "lat": 27.05102,
            "lng": 128.398723
          }
        },
        {
          "title": "与論空港 - panoramio",
          "description": "与論空港",
          "url": "https://upload.wikimedia.org/wikipedia/commons/thumb/b/b5/%E4%B8%8E%E8%AB%96%E7%A9%BA%E6%B8%AF_-_panoramio.jpg/960px-%E4%B8%8E%E8%AB%96%E7%A9%BA%E6%B8%AF_-_panoramio.jpg",
          "sourceUrl": "https://commons.wikimedia.org/wiki/File:%E4%B8%8E%E8%AB%96%E7%A9%BA%E6%B8%AF_-_panoramio.jpg",
          "credit": "daipresents",
          "license": "CC BY 3.0",
          "gps": {
            "lat": 27.043488,
            "lng": 128.400143
          }
        }
      ]
    },
    {
      "fraction": 0.4,
      "point": {
        "lat": 27.022556190114308,
        "lng": 128.43458883094507,
        "ele": 54.7
      },
      "stations": [],
      "photos": [
        {
          "title": "Yoron Port Kagoshima Kagoshima JAPAN",
          "description": "与論港",
          "url": "https://upload.wikimedia.org/wikipedia/commons/thumb/2/2e/Yoron_Port_Kagoshima_Kagoshima_JAPAN.jpg/960px-Yoron_Port_Kagoshima_Kagoshima_JAPAN.jpg",
          "sourceUrl": "https://commons.wikimedia.org/wiki/File:Yoron_Port_Kagoshima_Kagoshima_JAPAN.jpg",
          "credit": "Rsa",
          "license": "CC BY-SA 3.0",
          "gps": {
            "lat": 27.034966,
            "lng": 128.401648
          }
        },
        {
          "title": "Yoron PRICIA 0122",
          "description": "プリシアリゾート ヨロン 送迎バス",
          "url": "https://upload.wikimedia.org/wikipedia/commons/thumb/3/30/Yoron_PRICIA_0122.jpg/960px-Yoron_PRICIA_0122.jpg",
          "sourceUrl": "https://commons.wikimedia.org/wiki/File:Yoron_PRICIA_0122.jpg",
          "credit": "Rsa",
          "license": "CC BY-SA 3.0",
          "gps": {
            "lat": 27.036286,
            "lng": 128.401261
          }
        },
        {
          "title": "与論空港 - panoramio",
          "description": "与論空港",
          "url": "https://upload.wikimedia.org/wikipedia/commons/thumb/b/b5/%E4%B8%8E%E8%AB%96%E7%A9%BA%E6%B8%AF_-_panoramio.jpg/960px-%E4%B8%8E%E8%AB%96%E7%A9%BA%E6%B8%AF_-_panoramio.jpg",
          "sourceUrl": "https://commons.wikimedia.org/wiki/File:%E4%B8%8E%E8%AB%96%E7%A9%BA%E6%B8%AF_-_panoramio.jpg",
          "credit": "daipresents",
          "license": "CC BY 3.0",
          "gps": {
            "lat": 27.043488,
            "lng": 128.400143
          }
        },
        {
          "title": "Unnamed Road, Furusato, Yoron-chō, Ōshima-gun, Kagoshima-ken 891-9307, Japan - panoramio",
          "description": "Unnamed Road, Furusato, Yoron-chō, Ōshima-gun, Kagoshima-ken 891-9307, Japan",
          "url": "https://upload.wikimedia.org/wikipedia/commons/thumb/8/86/Unnamed_Road%2C_Furusato%2C_Yoron-ch%C5%8D%2C_%C5%8Cshima-gun%2C_Kagoshima-ken_891-9307%2C_Japan_-_panoramio.jpg/960px-Unnamed_Road%2C_Furusato%2C_Yoron-ch%C5%8D%2C_%C5%8Cshima-gun%2C_Kagoshima-ken_891-9307%2C_Japan_-_panoramio.jpg",
          "sourceUrl": "https://commons.wikimedia.org/wiki/File:Unnamed_Road,_Furusato,_Yoron-ch%C5%8D,_%C5%8Cshima-gun,_Kagoshima-ken_891-9307,_Japan_-_panoramio.jpg",
          "credit": "daipresents",
          "license": "CC BY 3.0",
          "gps": {
            "lat": 27.04899,
            "lng": 128.4632
          }
        },
        {
          "title": "夢とロマンをのせて マルエーフェリー (41549291204)",
          "description": "KIMG1441",
          "url": "https://upload.wikimedia.org/wikipedia/commons/thumb/6/69/%E5%A4%A2%E3%81%A8%E3%83%AD%E3%83%9E%E3%83%B3%E3%82%92%E3%81%AE%E3%81%9B%E3%81%A6_%E3%83%9E%E3%83%AB%E3%82%A8%E3%83%BC%E3%83%95%E3%82%A7%E3%83%AA%E3%83%BC_%2841549291204%29.jpg/960px-%E5%A4%A2%E3%81%A8%E3%83%AD%E3%83%9E%E3%83%B3%E3%82%92%E3%81%AE%E3%81%9B%E3%81%A6_%E3%83%9E%E3%83%AB%E3%82%A8%E3%83%BC%E3%83%95%E3%82%A7%E3%83%AA%E3%83%BC_%2841549291204%29.jpg",
          "sourceUrl": "https://commons.wikimedia.org/wiki/File:%E5%A4%A2%E3%81%A8%E3%83%AD%E3%83%9E%E3%83%B3%E3%82%92%E3%81%AE%E3%81%9B%E3%81%A6_%E3%83%9E%E3%83%AB%E3%82%A8%E3%83%BC%E3%83%95%E3%82%A7%E3%83%AA%E3%83%BC_(41549291204).jpg",
          "credit": "girakku",
          "license": "CC0",
          "gps": {
            "lat": 27.044469,
            "lng": 128.414486
          }
        },
        {
          "title": "2021-04-09 Chabana-gyoko 茶花漁港 DJI Mini2-0033",
          "description": "2021-04-09 Chabana-gyoko 茶花漁港",
          "url": "https://upload.wikimedia.org/wikipedia/commons/thumb/b/bc/2021-04-09_Chabana-gyoko_%E8%8C%B6%E8%8A%B1%E6%BC%81%E6%B8%AF_DJI_Mini2-0033.jpg/960px-2021-04-09_Chabana-gyoko_%E8%8C%B6%E8%8A%B1%E6%BC%81%E6%B8%AF_DJI_Mini2-0033.jpg",
          "sourceUrl": "https://commons.wikimedia.org/wiki/File:2021-04-09_Chabana-gyoko_%E8%8C%B6%E8%8A%B1%E6%BC%81%E6%B8%AF_DJI_Mini2-0033.jpg",
          "credit": "松岡明芳",
          "license": "CC BY-SA 4.0",
          "gps": {
            "lat": 27.051574,
            "lng": 128.413815
          }
        },
        {
          "title": "2021-04-09 Yoronjima-seito 与論島製糖（株）DJI Mini2-0023",
          "description": "2021-04-09 Yoronjima-seito 与論島製糖（株）",
          "url": "https://upload.wikimedia.org/wikipedia/commons/thumb/3/35/2021-04-09_Yoronjima-seito_%E4%B8%8E%E8%AB%96%E5%B3%B6%E8%A3%BD%E7%B3%96%EF%BC%88%E6%A0%AA%EF%BC%89DJI_Mini2-0023.jpg/960px-2021-04-09_Yoronjima-seito_%E4%B8%8E%E8%AB%96%E5%B3%B6%E8%A3%BD%E7%B3%96%EF%BC%88%E6%A0%AA%EF%BC%89DJI_Mini2-0023.jpg",
          "sourceUrl": "https://commons.wikimedia.org/wiki/File:2021-04-09_Yoronjima-seito_%E4%B8%8E%E8%AB%96%E5%B3%B6%E8%A3%BD%E7%B3%96%EF%BC%88%E6%A0%AA%EF%BC%89DJI_Mini2-0023.jpg",
          "credit": "松岡明芳",
          "license": "CC BY-SA 4.0",
          "gps": {
            "lat": 27.045763,
            "lng": 128.41205
          }
        },
        {
          "title": "2021-04-10 Beach Minata,Amami,Kagoshima (皆田海岸)-DJI Mini2-0043",
          "description": "2021-04-10 Beach Minata,Amami,Kagoshima (皆田海岸)",
          "url": "https://upload.wikimedia.org/wikipedia/commons/thumb/7/7c/2021-04-10_Beach_Minata%2CAmami%2CKagoshima_%28%E7%9A%86%E7%94%B0%E6%B5%B7%E5%B2%B8%29-DJI_Mini2-0043.jpg/960px-2021-04-10_Beach_Minata%2CAmami%2CKagoshima_%28%E7%9A%86%E7%94%B0%E6%B5%B7%E5%B2%B8%29-DJI_Mini2-0043.jpg",
          "sourceUrl": "https://commons.wikimedia.org/wiki/File:2021-04-10_Beach_Minata,Amami,Kagoshima_(%E7%9A%86%E7%94%B0%E6%B5%B7%E5%B2%B8)-DJI_Mini2-0043.jpg",
          "credit": "松岡明芳",
          "license": "CC BY-SA 4.0",
          "gps": {
            "lat": 27.054582,
            "lng": 128.449846
          }
        }
      ]
    },
    {
      "fraction": 0.6,
      "point": {
        "lat": 27.02968261172368,
        "lng": 128.45537629255176,
        "ele": 16.8
      },
      "stations": [],
      "photos": [
        {
          "title": "Yoron Port Kagoshima Kagoshima JAPAN",
          "description": "与論港",
          "url": "https://upload.wikimedia.org/wikipedia/commons/thumb/2/2e/Yoron_Port_Kagoshima_Kagoshima_JAPAN.jpg/960px-Yoron_Port_Kagoshima_Kagoshima_JAPAN.jpg",
          "sourceUrl": "https://commons.wikimedia.org/wiki/File:Yoron_Port_Kagoshima_Kagoshima_JAPAN.jpg",
          "credit": "Rsa",
          "license": "CC BY-SA 3.0",
          "gps": {
            "lat": 27.034966,
            "lng": 128.401648
          }
        },
        {
          "title": "Yoron PRICIA 0122",
          "description": "プリシアリゾート ヨロン 送迎バス",
          "url": "https://upload.wikimedia.org/wikipedia/commons/thumb/3/30/Yoron_PRICIA_0122.jpg/960px-Yoron_PRICIA_0122.jpg",
          "sourceUrl": "https://commons.wikimedia.org/wiki/File:Yoron_PRICIA_0122.jpg",
          "credit": "Rsa",
          "license": "CC BY-SA 3.0",
          "gps": {
            "lat": 27.036286,
            "lng": 128.401261
          }
        },
        {
          "title": "Unnamed Road, Furusato, Yoron-chō, Ōshima-gun, Kagoshima-ken 891-9307, Japan - panoramio",
          "description": "Unnamed Road, Furusato, Yoron-chō, Ōshima-gun, Kagoshima-ken 891-9307, Japan",
          "url": "https://upload.wikimedia.org/wikipedia/commons/thumb/8/86/Unnamed_Road%2C_Furusato%2C_Yoron-ch%C5%8D%2C_%C5%8Cshima-gun%2C_Kagoshima-ken_891-9307%2C_Japan_-_panoramio.jpg/960px-Unnamed_Road%2C_Furusato%2C_Yoron-ch%C5%8D%2C_%C5%8Cshima-gun%2C_Kagoshima-ken_891-9307%2C_Japan_-_panoramio.jpg",
          "sourceUrl": "https://commons.wikimedia.org/wiki/File:Unnamed_Road,_Furusato,_Yoron-ch%C5%8D,_%C5%8Cshima-gun,_Kagoshima-ken_891-9307,_Japan_-_panoramio.jpg",
          "credit": "daipresents",
          "license": "CC BY 3.0",
          "gps": {
            "lat": 27.04899,
            "lng": 128.4632
          }
        },
        {
          "title": "夢とロマンをのせて マルエーフェリー (41549291204)",
          "description": "KIMG1441",
          "url": "https://upload.wikimedia.org/wikipedia/commons/thumb/6/69/%E5%A4%A2%E3%81%A8%E3%83%AD%E3%83%9E%E3%83%B3%E3%82%92%E3%81%AE%E3%81%9B%E3%81%A6_%E3%83%9E%E3%83%AB%E3%82%A8%E3%83%BC%E3%83%95%E3%82%A7%E3%83%AA%E3%83%BC_%2841549291204%29.jpg/960px-%E5%A4%A2%E3%81%A8%E3%83%AD%E3%83%9E%E3%83%B3%E3%82%92%E3%81%AE%E3%81%9B%E3%81%A6_%E3%83%9E%E3%83%AB%E3%82%A8%E3%83%BC%E3%83%95%E3%82%A7%E3%83%AA%E3%83%BC_%2841549291204%29.jpg",
          "sourceUrl": "https://commons.wikimedia.org/wiki/File:%E5%A4%A2%E3%81%A8%E3%83%AD%E3%83%9E%E3%83%B3%E3%82%92%E3%81%AE%E3%81%9B%E3%81%A6_%E3%83%9E%E3%83%AB%E3%82%A8%E3%83%BC%E3%83%95%E3%82%A7%E3%83%AA%E3%83%BC_(41549291204).jpg",
          "credit": "girakku",
          "license": "CC0",
          "gps": {
            "lat": 27.044469,
            "lng": 128.414486
          }
        },
        {
          "title": "2021-04-09 Chabana-gyoko 茶花漁港 DJI Mini2-0033",
          "description": "2021-04-09 Chabana-gyoko 茶花漁港",
          "url": "https://upload.wikimedia.org/wikipedia/commons/thumb/b/bc/2021-04-09_Chabana-gyoko_%E8%8C%B6%E8%8A%B1%E6%BC%81%E6%B8%AF_DJI_Mini2-0033.jpg/960px-2021-04-09_Chabana-gyoko_%E8%8C%B6%E8%8A%B1%E6%BC%81%E6%B8%AF_DJI_Mini2-0033.jpg",
          "sourceUrl": "https://commons.wikimedia.org/wiki/File:2021-04-09_Chabana-gyoko_%E8%8C%B6%E8%8A%B1%E6%BC%81%E6%B8%AF_DJI_Mini2-0033.jpg",
          "credit": "松岡明芳",
          "license": "CC BY-SA 4.0",
          "gps": {
            "lat": 27.051574,
            "lng": 128.413815
          }
        },
        {
          "title": "2021-04-09 Yoronjima-seito 与論島製糖（株）DJI Mini2-0023",
          "description": "2021-04-09 Yoronjima-seito 与論島製糖（株）",
          "url": "https://upload.wikimedia.org/wikipedia/commons/thumb/3/35/2021-04-09_Yoronjima-seito_%E4%B8%8E%E8%AB%96%E5%B3%B6%E8%A3%BD%E7%B3%96%EF%BC%88%E6%A0%AA%EF%BC%89DJI_Mini2-0023.jpg/960px-2021-04-09_Yoronjima-seito_%E4%B8%8E%E8%AB%96%E5%B3%B6%E8%A3%BD%E7%B3%96%EF%BC%88%E6%A0%AA%EF%BC%89DJI_Mini2-0023.jpg",
          "sourceUrl": "https://commons.wikimedia.org/wiki/File:2021-04-09_Yoronjima-seito_%E4%B8%8E%E8%AB%96%E5%B3%B6%E8%A3%BD%E7%B3%96%EF%BC%88%E6%A0%AA%EF%BC%89DJI_Mini2-0023.jpg",
          "credit": "松岡明芳",
          "license": "CC BY-SA 4.0",
          "gps": {
            "lat": 27.045763,
            "lng": 128.41205
          }
        },
        {
          "title": "2021-04-10 Beach Minata,Amami,Kagoshima (皆田海岸)-DJI Mini2-0043",
          "description": "2021-04-10 Beach Minata,Amami,Kagoshima (皆田海岸)",
          "url": "https://upload.wikimedia.org/wikipedia/commons/thumb/7/7c/2021-04-10_Beach_Minata%2CAmami%2CKagoshima_%28%E7%9A%86%E7%94%B0%E6%B5%B7%E5%B2%B8%29-DJI_Mini2-0043.jpg/960px-2021-04-10_Beach_Minata%2CAmami%2CKagoshima_%28%E7%9A%86%E7%94%B0%E6%B5%B7%E5%B2%B8%29-DJI_Mini2-0043.jpg",
          "sourceUrl": "https://commons.wikimedia.org/wiki/File:2021-04-10_Beach_Minata,Amami,Kagoshima_(%E7%9A%86%E7%94%B0%E6%B5%B7%E5%B2%B8)-DJI_Mini2-0043.jpg",
          "credit": "松岡明芳",
          "license": "CC BY-SA 4.0",
          "gps": {
            "lat": 27.054582,
            "lng": 128.449846
          }
        },
        {
          "title": "2021-04-10 Beach Minata,Amami,Kagoshima (皆田海岸) DJI Mini2-0048",
          "description": "2021-04-10 Beach Minata,Amami,Kagoshima (皆田海岸)",
          "url": "https://upload.wikimedia.org/wikipedia/commons/thumb/a/aa/2021-04-10_Beach_Minata%2CAmami%2CKagoshima_%28%E7%9A%86%E7%94%B0%E6%B5%B7%E5%B2%B8%29_DJI_Mini2-0048.jpg/960px-2021-04-10_Beach_Minata%2CAmami%2CKagoshima_%28%E7%9A%86%E7%94%B0%E6%B5%B7%E5%B2%B8%29_DJI_Mini2-0048.jpg",
          "sourceUrl": "https://commons.wikimedia.org/wiki/File:2021-04-10_Beach_Minata,Amami,Kagoshima_(%E7%9A%86%E7%94%B0%E6%B5%B7%E5%B2%B8)_DJI_Mini2-0048.jpg",
          "credit": "松岡明芳",
          "license": "CC BY-SA 4.0",
          "gps": {
            "lat": 27.053459,
            "lng": 128.451878
          }
        }
      ]
    },
    {
      "fraction": 0.8,
      "point": {
        "lat": 27.06340129366159,
        "lng": 128.43872589335643,
        "ele": 22.7
      },
      "stations": [],
      "photos": [
        {
          "title": "プリシアリゾート",
          "description": "プリシアリゾート",
          "url": "https://upload.wikimedia.org/wikipedia/commons/thumb/b/b6/%E3%83%97%E3%83%AA%E3%82%B7%E3%82%A2%E3%83%AA%E3%82%BE%E3%83%BC%E3%83%88.jpg/960px-%E3%83%97%E3%83%AA%E3%82%B7%E3%82%A2%E3%83%AA%E3%82%BE%E3%83%BC%E3%83%88.jpg",
          "sourceUrl": "https://commons.wikimedia.org/wiki/File:%E3%83%97%E3%83%AA%E3%82%B7%E3%82%A2%E3%83%AA%E3%82%BE%E3%83%BC%E3%83%88.jpg",
          "credit": "daipresents",
          "license": "CC BY 3.0",
          "gps": {
            "lat": 27.050859,
            "lng": 128.398993
          }
        },
        {
          "title": "与論の海の中 - panoramio",
          "description": "与論の海の中",
          "url": "https://upload.wikimedia.org/wikipedia/commons/thumb/e/ec/%E4%B8%8E%E8%AB%96%E3%81%AE%E6%B5%B7%E3%81%AE%E4%B8%AD_-_panoramio.jpg/960px-%E4%B8%8E%E8%AB%96%E3%81%AE%E6%B5%B7%E3%81%AE%E4%B8%AD_-_panoramio.jpg",
          "sourceUrl": "https://commons.wikimedia.org/wiki/File:%E4%B8%8E%E8%AB%96%E3%81%AE%E6%B5%B7%E3%81%AE%E4%B8%AD_-_panoramio.jpg",
          "credit": "daipresents",
          "license": "CC BY 3.0",
          "gps": {
            "lat": 27.063054,
            "lng": 128.41256
          }
        },
        {
          "title": "Unnamed Road, Furusato, Yoron-chō, Ōshima-gun, Kagoshima-ken 891-9307, Japan - panoramio",
          "description": "Unnamed Road, Furusato, Yoron-chō, Ōshima-gun, Kagoshima-ken 891-9307, Japan",
          "url": "https://upload.wikimedia.org/wikipedia/commons/thumb/8/86/Unnamed_Road%2C_Furusato%2C_Yoron-ch%C5%8D%2C_%C5%8Cshima-gun%2C_Kagoshima-ken_891-9307%2C_Japan_-_panoramio.jpg/960px-Unnamed_Road%2C_Furusato%2C_Yoron-ch%C5%8D%2C_%C5%8Cshima-gun%2C_Kagoshima-ken_891-9307%2C_Japan_-_panoramio.jpg",
          "sourceUrl": "https://commons.wikimedia.org/wiki/File:Unnamed_Road,_Furusato,_Yoron-ch%C5%8D,_%C5%8Cshima-gun,_Kagoshima-ken_891-9307,_Japan_-_panoramio.jpg",
          "credit": "daipresents",
          "license": "CC BY 3.0",
          "gps": {
            "lat": 27.04899,
            "lng": 128.4632
          }
        },
        {
          "title": "夢とロマンをのせて マルエーフェリー (41549291204)",
          "description": "KIMG1441",
          "url": "https://upload.wikimedia.org/wikipedia/commons/thumb/6/69/%E5%A4%A2%E3%81%A8%E3%83%AD%E3%83%9E%E3%83%B3%E3%82%92%E3%81%AE%E3%81%9B%E3%81%A6_%E3%83%9E%E3%83%AB%E3%82%A8%E3%83%BC%E3%83%95%E3%82%A7%E3%83%AA%E3%83%BC_%2841549291204%29.jpg/960px-%E5%A4%A2%E3%81%A8%E3%83%AD%E3%83%9E%E3%83%B3%E3%82%92%E3%81%AE%E3%81%9B%E3%81%A6_%E3%83%9E%E3%83%AB%E3%82%A8%E3%83%BC%E3%83%95%E3%82%A7%E3%83%AA%E3%83%BC_%2841549291204%29.jpg",
          "sourceUrl": "https://commons.wikimedia.org/wiki/File:%E5%A4%A2%E3%81%A8%E3%83%AD%E3%83%9E%E3%83%B3%E3%82%92%E3%81%AE%E3%81%9B%E3%81%A6_%E3%83%9E%E3%83%AB%E3%82%A8%E3%83%BC%E3%83%95%E3%82%A7%E3%83%AA%E3%83%BC_(41549291204).jpg",
          "credit": "girakku",
          "license": "CC0",
          "gps": {
            "lat": 27.044469,
            "lng": 128.414486
          }
        },
        {
          "title": "2021-04-09 Chabana-gyoko 茶花漁港 DJI Mini2-0033",
          "description": "2021-04-09 Chabana-gyoko 茶花漁港",
          "url": "https://upload.wikimedia.org/wikipedia/commons/thumb/b/bc/2021-04-09_Chabana-gyoko_%E8%8C%B6%E8%8A%B1%E6%BC%81%E6%B8%AF_DJI_Mini2-0033.jpg/960px-2021-04-09_Chabana-gyoko_%E8%8C%B6%E8%8A%B1%E6%BC%81%E6%B8%AF_DJI_Mini2-0033.jpg",
          "sourceUrl": "https://commons.wikimedia.org/wiki/File:2021-04-09_Chabana-gyoko_%E8%8C%B6%E8%8A%B1%E6%BC%81%E6%B8%AF_DJI_Mini2-0033.jpg",
          "credit": "松岡明芳",
          "license": "CC BY-SA 4.0",
          "gps": {
            "lat": 27.051574,
            "lng": 128.413815
          }
        },
        {
          "title": "2021-04-09 Yoronjima-seito 与論島製糖（株）DJI Mini2-0023",
          "description": "2021-04-09 Yoronjima-seito 与論島製糖（株）",
          "url": "https://upload.wikimedia.org/wikipedia/commons/thumb/3/35/2021-04-09_Yoronjima-seito_%E4%B8%8E%E8%AB%96%E5%B3%B6%E8%A3%BD%E7%B3%96%EF%BC%88%E6%A0%AA%EF%BC%89DJI_Mini2-0023.jpg/960px-2021-04-09_Yoronjima-seito_%E4%B8%8E%E8%AB%96%E5%B3%B6%E8%A3%BD%E7%B3%96%EF%BC%88%E6%A0%AA%EF%BC%89DJI_Mini2-0023.jpg",
          "sourceUrl": "https://commons.wikimedia.org/wiki/File:2021-04-09_Yoronjima-seito_%E4%B8%8E%E8%AB%96%E5%B3%B6%E8%A3%BD%E7%B3%96%EF%BC%88%E6%A0%AA%EF%BC%89DJI_Mini2-0023.jpg",
          "credit": "松岡明芳",
          "license": "CC BY-SA 4.0",
          "gps": {
            "lat": 27.045763,
            "lng": 128.41205
          }
        },
        {
          "title": "2021-04-10 Beach Minata,Amami,Kagoshima (皆田海岸)-DJI Mini2-0043",
          "description": "2021-04-10 Beach Minata,Amami,Kagoshima (皆田海岸)",
          "url": "https://upload.wikimedia.org/wikipedia/commons/thumb/7/7c/2021-04-10_Beach_Minata%2CAmami%2CKagoshima_%28%E7%9A%86%E7%94%B0%E6%B5%B7%E5%B2%B8%29-DJI_Mini2-0043.jpg/960px-2021-04-10_Beach_Minata%2CAmami%2CKagoshima_%28%E7%9A%86%E7%94%B0%E6%B5%B7%E5%B2%B8%29-DJI_Mini2-0043.jpg",
          "sourceUrl": "https://commons.wikimedia.org/wiki/File:2021-04-10_Beach_Minata,Amami,Kagoshima_(%E7%9A%86%E7%94%B0%E6%B5%B7%E5%B2%B8)-DJI_Mini2-0043.jpg",
          "credit": "松岡明芳",
          "license": "CC BY-SA 4.0",
          "gps": {
            "lat": 27.054582,
            "lng": 128.449846
          }
        },
        {
          "title": "2021-04-10 Beach Minata,Amami,Kagoshima (皆田海岸) DJI Mini2-0048",
          "description": "2021-04-10 Beach Minata,Amami,Kagoshima (皆田海岸)",
          "url": "https://upload.wikimedia.org/wikipedia/commons/thumb/a/aa/2021-04-10_Beach_Minata%2CAmami%2CKagoshima_%28%E7%9A%86%E7%94%B0%E6%B5%B7%E5%B2%B8%29_DJI_Mini2-0048.jpg/960px-2021-04-10_Beach_Minata%2CAmami%2CKagoshima_%28%E7%9A%86%E7%94%B0%E6%B5%B7%E5%B2%B8%29_DJI_Mini2-0048.jpg",
          "sourceUrl": "https://commons.wikimedia.org/wiki/File:2021-04-10_Beach_Minata,Amami,Kagoshima_(%E7%9A%86%E7%94%B0%E6%B5%B7%E5%B2%B8)_DJI_Mini2-0048.jpg",
          "credit": "松岡明芳",
          "license": "CC BY-SA 4.0",
          "gps": {
            "lat": 27.053459,
            "lng": 128.451878
          }
        }
      ]
    }
  ],
  "reviewStatus": "needs_review"
}
