{
  "slug": "kanazawa-castle-loop",
  "heroCheckpointId": "section-1",
  "checkpointsTitle": "コースの雰囲気",
  "intro": "金沢マラソンのランニングコースマップでも公式に案内される定番で、金沢城周遊コースは約2.1kmです。石川門や石垣を眺めながら走れ、中心部らしい歴史景観を感じられます。距離が手頃で周回管理しやすく、旅ランでも使いやすいのが利点です。スピード練習よりはジョグや一定ペースの周回に向き、兼六園周辺の観光と組み合わせやすい、金沢市内で知名度の高い一周です。目的に応じて本数や往復回数を調整しやすい点も実用的です。",
  "warnings": [
    {
      "title": "一般利用者と交通ルールを優先してください",
      "body": "ランニング専用路ではない区間を含む場合があります。信号を守り、歩道・公園・河川敷では歩行者を優先し、混雑時は歩いて通過してください。",
      "url": "https://www.npa.go.jp/bureau/traffic/koutsuuannzennjyouhou.html",
      "linkLabel": "警察庁の交通安全情報"
    },
    {
      "title": "コースデータは出発前にも確認してください",
      "body": "アクセス情報: 北陸鉄道バス「兼六園下・金沢城」下車徒歩約5分。 工事や災害、施設の営業時間などは変わるため、現地案内を優先してください。",
      "url": "https://dokorun.com/guide/gpx",
      "linkLabel": "どこランのGPX利用ガイド"
    }
  ],
  "startPoints": [
    {
      "id": "start-1",
      "name": "北鉄金沢駅側",
      "badge": "電車でアクセス",
      "destinationLat": 36.578637,
      "destinationLng": 136.649524,
      "routeAnchorLat": 36.568494,
      "routeAnchorLng": 136.660773,
      "routeMode": "loop",
      "accessText": "北鉄金沢駅からコースまで約1510m",
      "facilitiesText": "設備欄と現地案内を出発前に確認してください",
      "firstSection": "地図とGPXで最初の分岐を確認してから走り始めます。"
    },
    {
      "id": "start-2",
      "name": "金沢駅側",
      "badge": "電車でアクセス",
      "destinationLat": 36.578117,
      "destinationLng": 136.648166,
      "routeAnchorLat": 36.565505,
      "routeAnchorLng": 136.656441,
      "routeMode": "loop",
      "accessText": "金沢駅からコースまで約1590m",
      "facilitiesText": "設備欄と現地案内を出発前に確認してください",
      "firstSection": "地図とGPXで最初の分岐を確認してから走り始めます。"
    },
    {
      "id": "start-3",
      "name": "野町駅側",
      "badge": "電車でアクセス",
      "destinationLat": 36.553779,
      "destinationLng": 136.644309,
      "routeAnchorLat": 36.563035,
      "routeAnchorLng": 136.659465,
      "routeMode": "loop",
      "accessText": "野町駅からコースまで約1700m",
      "facilitiesText": "設備欄と現地案内を出発前に確認してください",
      "firstSection": "地図とGPXで最初の分岐を確認してから走り始めます。"
    }
  ],
  "checkpoints": [
    {
      "id": "section-1",
      "name": "スタート周辺",
      "anchorLat": 36.568494,
      "anchorLng": 136.660773,
      "description": "スタート周辺の走路近隣で撮影された写真です。写真の説明: 金沢城河北門の遠景",
      "surfaceLabel": "舗装路",
      "caution": "歩行者と交差点を優先",
      "photo": {
        "url": "https://upload.wikimedia.org/wikipedia/commons/thumb/7/7b/View_of_Kahoku_Gate_of_Kanazawa_Castle.JPG/960px-View_of_Kahoku_Gate_of_Kanazawa_Castle.JPG",
        "alt": "金沢城公園外周のスタート周辺付近",
        "caption": "金沢城公園外周の走路近隣で撮影された風景",
        "credit": "そらみみ",
        "license": "CC BY-SA 4.0",
        "sourceUrl": "https://commons.wikimedia.org/wiki/File:View_of_Kahoku_Gate_of_Kanazawa_Castle.JPG"
      }
    },
    {
      "id": "section-2",
      "name": "序盤区間",
      "anchorLat": 36.569039,
      "anchorLng": 136.657098,
      "description": "序盤区間の走路近隣で撮影された写真です。写真の説明: 金沢城下・旧高峰家住宅(黒門前緑地)",
      "surfaceLabel": "舗装路",
      "caution": "歩行者と交差点を優先",
      "photo": {
        "url": "https://upload.wikimedia.org/wikipedia/commons/thumb/b/bc/Kuromonmae_Park_near_Kanazawa_Castle.JPG/960px-Kuromonmae_Park_near_Kanazawa_Castle.JPG",
        "alt": "金沢城公園外周の序盤区間付近",
        "caption": "金沢城公園外周の走路近隣で撮影された風景",
        "credit": "そらみみ",
        "license": "CC BY-SA 4.0",
        "sourceUrl": "https://commons.wikimedia.org/wiki/File:Kuromonmae_Park_near_Kanazawa_Castle.JPG"
      }
    },
    {
      "id": "section-3",
      "name": "中盤区間",
      "anchorLat": 36.565505,
      "anchorLng": 136.656441,
      "description": "中盤区間の走路近隣で撮影された写真です。写真の説明: 尾山神社境内・景仰之燈。奥に金沢城の石垣が見える",
      "surfaceLabel": "舗装路",
      "caution": "歩行者と交差点を優先",
      "photo": {
        "url": "https://upload.wikimedia.org/wikipedia/commons/thumb/5/5e/Admired_lamp_in_Oyama_Shrine.JPG/960px-Admired_lamp_in_Oyama_Shrine.JPG",
        "alt": "金沢城公園外周の中盤区間付近",
        "caption": "金沢城公園外周の走路近隣で撮影された風景",
        "credit": "そらみみ",
        "license": "CC BY-SA 4.0",
        "sourceUrl": "https://commons.wikimedia.org/wiki/File:Admired_lamp_in_Oyama_Shrine.JPG"
      }
    },
    {
      "id": "section-4",
      "name": "後半区間",
      "anchorLat": 36.563035,
      "anchorLng": 136.659465,
      "description": "後半区間の走路近隣で撮影された写真です。写真の説明: Kanazawa Castle Park",
      "surfaceLabel": "舗装路",
      "caution": "歩行者と交差点を優先",
      "photo": {
        "url": "https://upload.wikimedia.org/wikipedia/commons/thumb/8/89/Kanazawa_Castle_park_-_01_-_2016-04-16.jpg/960px-Kanazawa_Castle_park_-_01_-_2016-04-16.jpg",
        "alt": "金沢城公園外周の後半区間付近",
        "caption": "金沢城公園外周の走路近隣で撮影された風景",
        "credit": "MathieuMD",
        "license": "CC BY-SA 4.0",
        "sourceUrl": "https://commons.wikimedia.org/wiki/File:Kanazawa_Castle_park_-_01_-_2016-04-16.jpg"
      }
    },
    {
      "id": "section-5",
      "name": "終盤区間",
      "anchorLat": 36.565257,
      "anchorLng": 136.66207,
      "description": "終盤区間の走路近隣で撮影された写真です。写真の説明: 金沢城・石川橋より望む石川県道10号(国道159号方面)",
      "surfaceLabel": "舗装路",
      "caution": "歩行者と交差点を優先",
      "photo": {
        "url": "https://upload.wikimedia.org/wikipedia/commons/thumb/0/0f/Ishikawa_Prefectural_Road_No.10_from_Ishikawabashi_Bridge_in_front_of_Kanazawa_Castle.JPG/960px-Ishikawa_Prefectural_Road_No.10_from_Ishikawabashi_Bridge_in_front_of_Kanazawa_Castle.JPG",
        "alt": "金沢城公園外周の終盤区間付近",
        "caption": "金沢城公園外周の走路近隣で撮影された風景",
        "credit": "そらみみ",
        "license": "CC BY-SA 4.0",
        "sourceUrl": "https://commons.wikimedia.org/wiki/File:Ishikawa_Prefectural_Road_No.10_from_Ishikawabashi_Bridge_in_front_of_Kanazawa_Castle.JPG"
      }
    }
  ],
  "dataProvenance": {
    "stations": "HeartRails Express",
    "photos": "Wikimedia Commons geotagged media",
    "status": "automated_review_passed"
  }
}
